{
  "migrations": {
    "columns": [
      {
        "name": "id",
        "type": "INTEGER",
        "notnull": 0,
        "dflt_value": null,
        "pk": 1
      },
      {
        "name": "version",
        "type": "INTEGER",
        "notnull": 1,
        "dflt_value": null,
        "pk": 0
      },
      {
        "name": "name",
        "type": "TEXT",
        "notnull": 1,
        "dflt_value": null,
        "pk": 0
      },
      {
        "name": "applied_at",
        "type": "DATETIME",
        "notnull": 0,
        "dflt_value": "CURRENT_TIMESTAMP",
        "pk": 0
      }
    ]
  },
  "refresh_tokens": {
    "columns": [
      {
        "name": "tenant_id",
        "type": "INTEGER",
        "notnull": 0,
        "dflt_value": "1",
        "pk": 0
      },
      {
        "name": "id",
        "type": "INTEGER",
        "notnull": 0,
        "dflt_value": null,
        "pk": 1
      },
      {
        "name": "user_id",
        "type": "INTEGER",
        "notnull": 1,
        "dflt_value": null,
        "pk": 0
      },
      {
        "name": "token",
        "type": "VARCHAR(500)",
        "notnull": 1,
        "dflt_value": null,
        "pk": 0
      },
      {
        "name": "expires_at",
        "type": "DATETIME",
        "notnull": 1,
        "dflt_value": null,
        "pk": 0
      },
      {
        "name": "created_at",
        "type": "DATETIME",
        "notnull": 0,
        "dflt_value": "CURRENT_TIMESTAMP",
        "pk": 0
      }
    ]
  },
  "password_reset_tokens": {
    "columns": [
      {
        "name": "tenant_id",
        "type": "INTEGER",
        "notnull": 0,
        "dflt_value": "1",
        "pk": 0
      },
      {
        "name": "id",
        "type": "INTEGER",
        "notnull": 0,
        "dflt_value": null,
        "pk": 1
      },
      {
        "name": "user_id",
        "type": "INTEGER",
        "notnull": 1,
        "dflt_value": null,
        "pk": 0
      },
      {
        "name": "token",
        "type": "VARCHAR(500)",
        "notnull": 1,
        "dflt_value": null,
        "pk": 0
      },
      {
        "name": "expires_at",
        "type": "DATETIME",
        "notnull": 1,
        "dflt_value": null,
        "pk": 0
      },
      {
        "name": "used",
        "type": "BOOLEAN",
        "notnull": 0,
        "dflt_value": "FALSE",
        "pk": 0
      },
      {
        "name": "created_at",
        "type": "DATETIME",
        "notnull": 0,
        "dflt_value": "CURRENT_TIMESTAMP",
        "pk": 0
      },
      {
        "name": "token_hash",
        "type": "TEXT",
        "notnull": 0,
        "dflt_value": null,
        "pk": 0
      }
    ]
  },
  "audit_logs": {
    "columns": [
      {
        "name": "tenant_id",
        "type": "INTEGER",
        "notnull": 0,
        "dflt_value": "1",
        "pk": 0
      },
      {
        "name": "id",
        "type": "INTEGER",
        "notnull": 0,
        "dflt_value": null,
        "pk": 1
      },
      {
        "name": "user_id",
        "type": "INTEGER",
        "notnull": 0,
        "dflt_value": null,
        "pk": 0
      },
      {
        "name": "action",
        "type": "VARCHAR(100)",
        "notnull": 1,
        "dflt_value": null,
        "pk": 0
      },
      {
        "name": "table_name",
        "type": "VARCHAR(100)",
        "notnull": 1,
        "dflt_value": null,
        "pk": 0
      },
      {
        "name": "record_id",
        "type": "INTEGER",
        "notnull": 0,
        "dflt_value": null,
        "pk": 0
      },
      {
        "name": "old_values",
        "type": "TEXT",
        "notnull": 0,
        "dflt_value": null,
        "pk": 0
      },
      {
        "name": "new_values",
        "type": "TEXT",
        "notnull": 0,
        "dflt_value": null,
        "pk": 0
      },
      {
        "name": "ip_address",
        "type": "VARCHAR(45)",
        "notnull": 0,
        "dflt_value": null,
        "pk": 0
      },
      {
        "name": "user_agent",
        "type": "TEXT",
        "notnull": 0,
        "dflt_value": null,
        "pk": 0
      },
      {
        "name": "created_at",
        "type": "DATETIME",
        "notnull": 0,
        "dflt_value": "CURRENT_TIMESTAMP",
        "pk": 0
      }
    ]
  },
  "ayarlar_genel_isletme_ayarlari": {
    "columns": [
      {
        "name": "tenant_id",
        "type": "INTEGER",
        "notnull": 0,
        "dflt_value": "1",
        "pk": 0
      },
      {
        "name": "id",
        "type": "INTEGER",
        "notnull": 0,
        "dflt_value": null,
        "pk": 1
      },
      {
        "name": "isletme_adi",
        "type": "TEXT",
        "notnull": 1,
        "dflt_value": null,
        "pk": 0
      },
      {
        "name": "yetkili_kisi",
        "type": "TEXT",
        "notnull": 0,
        "dflt_value": null,
        "pk": 0
      },
      {
        "name": "telefon",
        "type": "TEXT",
        "notnull": 0,
        "dflt_value": null,
        "pk": 0
      },
      {
        "name": "whatsapp",
        "type": "TEXT",
        "notnull": 0,
        "dflt_value": null,
        "pk": 0
      },
      {
        "name": "eposta",
        "type": "TEXT",
        "notnull": 0,
        "dflt_value": null,
        "pk": 0
      },
      {
        "name": "website",
        "type": "TEXT",
        "notnull": 0,
        "dflt_value": null,
        "pk": 0
      },
      {
        "name": "vergi_dairesi",
        "type": "TEXT",
        "notnull": 0,
        "dflt_value": null,
        "pk": 0
      },
      {
        "name": "vergi_no",
        "type": "TEXT",
        "notnull": 0,
        "dflt_value": null,
        "pk": 0
      },
      {
        "name": "il",
        "type": "TEXT",
        "notnull": 0,
        "dflt_value": null,
        "pk": 0
      },
      {
        "name": "ilce",
        "type": "TEXT",
        "notnull": 0,
        "dflt_value": null,
        "pk": 0
      },
      {
        "name": "adres",
        "type": "TEXT",
        "notnull": 0,
        "dflt_value": null,
        "pk": 0
      },
      {
        "name": "logo_path",
        "type": "TEXT",
        "notnull": 0,
        "dflt_value": null,
        "pk": 0
      },
      {
        "name": "created_at",
        "type": "DATETIME",
        "notnull": 0,
        "dflt_value": "CURRENT_TIMESTAMP",
        "pk": 0
      },
      {
        "name": "updated_at",
        "type": "DATETIME",
        "notnull": 0,
        "dflt_value": "CURRENT_TIMESTAMP",
        "pk": 0
      },
      {
        "name": "created_by",
        "type": "TEXT",
        "notnull": 0,
        "dflt_value": null,
        "pk": 0
      },
      {
        "name": "updated_by",
        "type": "TEXT",
        "notnull": 0,
        "dflt_value": null,
        "pk": 0
      },
      {
        "name": "is_active",
        "type": "INTEGER",
        "notnull": 0,
        "dflt_value": "1",
        "pk": 0
      }
    ]
  },
  "ayarlar_genel_gonderim_ayarlari": {
    "columns": [
      {
        "name": "tenant_id",
        "type": "INTEGER",
        "notnull": 0,
        "dflt_value": "1",
        "pk": 0
      },
      {
        "name": "id",
        "type": "INTEGER",
        "notnull": 0,
        "dflt_value": null,
        "pk": 1
      },
      {
        "name": "siparis_listesi_whatsapp",
        "type": "TEXT",
        "notnull": 0,
        "dflt_value": null,
        "pk": 0
      },
      {
        "name": "musteri_sablonu_whatsapp",
        "type": "TEXT",
        "notnull": 0,
        "dflt_value": null,
        "pk": 0
      },
      {
        "name": "haftalik_rapor_eposta",
        "type": "TEXT",
        "notnull": 0,
        "dflt_value": null,
        "pk": 0
      },
      {
        "name": "created_at",
        "type": "DATETIME",
        "notnull": 0,
        "dflt_value": "CURRENT_TIMESTAMP",
        "pk": 0
      },
      {
        "name": "updated_at",
        "type": "DATETIME",
        "notnull": 0,
        "dflt_value": "CURRENT_TIMESTAMP",
        "pk": 0
      },
      {
        "name": "haftalik_rapor_gun",
        "type": "TEXT",
        "notnull": 0,
        "dflt_value": "\"1\"",
        "pk": 0
      },
      {
        "name": "created_by",
        "type": "TEXT",
        "notnull": 0,
        "dflt_value": null,
        "pk": 0
      },
      {
        "name": "updated_by",
        "type": "TEXT",
        "notnull": 0,
        "dflt_value": null,
        "pk": 0
      },
      {
        "name": "is_active",
        "type": "INTEGER",
        "notnull": 0,
        "dflt_value": "1",
        "pk": 0
      }
    ]
  },
  "ayarlar_genel_konum_ayarlari": {
    "columns": [
      {
        "name": "tenant_id",
        "type": "INTEGER",
        "notnull": 0,
        "dflt_value": "1",
        "pk": 0
      },
      {
        "name": "id",
        "type": "INTEGER",
        "notnull": 0,
        "dflt_value": null,
        "pk": 1
      },
      {
        "name": "il_id",
        "type": "TEXT",
        "notnull": 0,
        "dflt_value": null,
        "pk": 0
      },
      {
        "name": "il_adi",
        "type": "TEXT",
        "notnull": 0,
        "dflt_value": null,
        "pk": 0
      },
      {
        "name": "ilce_id",
        "type": "TEXT",
        "notnull": 0,
        "dflt_value": null,
        "pk": 0
      },
      {
        "name": "ilce_adi",
        "type": "TEXT",
        "notnull": 0,
        "dflt_value": null,
        "pk": 0
      },
      {
        "name": "created_at",
        "type": "DATETIME",
        "notnull": 0,
        "dflt_value": "CURRENT_TIMESTAMP",
        "pk": 0
      },
      {
        "name": "updated_at",
        "type": "DATETIME",
        "notnull": 0,
        "dflt_value": "CURRENT_TIMESTAMP",
        "pk": 0
      },
      {
        "name": "created_by",
        "type": "TEXT",
        "notnull": 0,
        "dflt_value": null,
        "pk": 0
      },
      {
        "name": "updated_by",
        "type": "TEXT",
        "notnull": 0,
        "dflt_value": null,
        "pk": 0
      },
      {
        "name": "is_active",
        "type": "INTEGER",
        "notnull": 0,
        "dflt_value": "1",
        "pk": 0
      }
    ]
  },
  "gps_konum_gecmisi": {
    "columns": [
      {
        "name": "tenant_id",
        "type": "INTEGER",
        "notnull": 0,
        "dflt_value": "1",
        "pk": 0
      },
      {
        "name": "id",
        "type": "INTEGER",
        "notnull": 0,
        "dflt_value": null,
        "pk": 1
      },
      {
        "name": "arac_id",
        "type": "INTEGER",
        "notnull": 1,
        "dflt_value": null,
        "pk": 0
      },
      {
        "name": "surucu_id",
        "type": "INTEGER",
        "notnull": 0,
        "dflt_value": null,
        "pk": 0
      },
      {
        "name": "latitude",
        "type": "DECIMAL(10, 8)",
        "notnull": 1,
        "dflt_value": null,
        "pk": 0
      },
      {
        "name": "longitude",
        "type": "DECIMAL(11, 8)",
        "notnull": 1,
        "dflt_value": null,
        "pk": 0
      },
      {
        "name": "hiz",
        "type": "DECIMAL(5, 2)",
        "notnull": 0,
        "dflt_value": null,
        "pk": 0
      },
      {
        "name": "yon",
        "type": "INTEGER",
        "notnull": 0,
        "dflt_value": null,
        "pk": 0
      },
      {
        "name": "yukseklik",
        "type": "DECIMAL(8, 2)",
        "notnull": 0,
        "dflt_value": null,
        "pk": 0
      },
      {
        "name": "dogruluk",
        "type": "DECIMAL(8, 2)",
        "notnull": 0,
        "dflt_value": null,
        "pk": 0
      },
      {
        "name": "konum_adi",
        "type": "VARCHAR(255)",
        "notnull": 0,
        "dflt_value": null,
        "pk": 0
      },
      {
        "name": "kayit_zamani",
        "type": "DATETIME",
        "notnull": 0,
        "dflt_value": "CURRENT_TIMESTAMP",
        "pk": 0
      }
    ]
  },
  "kart_turleri": {
    "columns": [
      {
        "name": "tenant_id",
        "type": "INTEGER",
        "notnull": 0,
        "dflt_value": "1",
        "pk": 0
      },
      {
        "name": "id",
        "type": "INTEGER",
        "notnull": 0,
        "dflt_value": null,
        "pk": 1
      },
      {
        "name": "tur_adi",
        "type": "VARCHAR (50)",
        "notnull": 1,
        "dflt_value": null,
        "pk": 0
      },
      {
        "name": "tur_aciklama",
        "type": "VARCHAR (255)",
        "notnull": 0,
        "dflt_value": null,
        "pk": 0
      },
      {
        "name": "renk_kodu",
        "type": "VARCHAR (7)",
        "notnull": 0,
        "dflt_value": null,
        "pk": 0
      },
      {
        "name": "icon_class",
        "type": "VARCHAR (100)",
        "notnull": 0,
        "dflt_value": null,
        "pk": 0
      },
      {
        "name": "created_at",
        "type": "DATETIME",
        "notnull": 0,
        "dflt_value": "CURRENT_TIMESTAMP",
        "pk": 0
      },
      {
        "name": "durum",
        "type": "INTEGER",
        "notnull": 0,
        "dflt_value": "1",
        "pk": 0
      },
      {
        "name": "is_active",
        "type": "BOOLEAN",
        "notnull": 0,
        "dflt_value": "\"TRUE\"",
        "pk": 0
      }
    ]
  },
  "ayarlar_ciceksepeti_ayalari": {
    "columns": [
      {
        "name": "tenant_id",
        "type": "INTEGER",
        "notnull": 0,
        "dflt_value": "1",
        "pk": 0
      },
      {
        "name": "id",
        "type": "INTEGER",
        "notnull": 0,
        "dflt_value": null,
        "pk": 1
      },
      {
        "name": "api_key",
        "type": "TEXT",
        "notnull": 0,
        "dflt_value": null,
        "pk": 0
      },
      {
        "name": "api_secret",
        "type": "TEXT",
        "notnull": 0,
        "dflt_value": null,
        "pk": 0
      },
      {
        "name": "api_mode",
        "type": "TEXT",
        "notnull": 0,
        "dflt_value": "'test'",
        "pk": 0
      },
      {
        "name": "webhook_url",
        "type": "TEXT",
        "notnull": 0,
        "dflt_value": null,
        "pk": 0
      },
      {
        "name": "siparis_kontrol",
        "type": "INTEGER",
        "notnull": 0,
        "dflt_value": "60",
        "pk": 0
      },
      {
        "name": "otomatik_onay",
        "type": "BOOLEAN",
        "notnull": 0,
        "dflt_value": "0",
        "pk": 0
      },
      {
        "name": "ses_bildirimi",
        "type": "BOOLEAN",
        "notnull": 0,
        "dflt_value": "1",
        "pk": 0
      },
      {
        "name": "created_at",
        "type": "DATETIME",
        "notnull": 0,
        "dflt_value": "CURRENT_TIMESTAMP",
        "pk": 0
      },
      {
        "name": "updated_at",
        "type": "DATETIME",
        "notnull": 0,
        "dflt_value": "CURRENT_TIMESTAMP",
        "pk": 0
      },
      {
        "name": "created_by",
        "type": "TEXT",
        "notnull": 0,
        "dflt_value": null,
        "pk": 0
      },
      {
        "name": "updated_by",
        "type": "TEXT",
        "notnull": 0,
        "dflt_value": null,
        "pk": 0
      },
      {
        "name": "is_active",
        "type": "INTEGER",
        "notnull": 0,
        "dflt_value": "1",
        "pk": 0
      }
    ]
  },
  "partner_siparisler": {
    "columns": [
      {
        "name": "tenant_id",
        "type": "INTEGER",
        "notnull": 0,
        "dflt_value": "1",
        "pk": 0
      },
      {
        "name": "id",
        "type": "INTEGER",
        "notnull": 0,
        "dflt_value": null,
        "pk": 1
      },
      {
        "name": "siparis_id",
        "type": "INTEGER",
        "notnull": 1,
        "dflt_value": null,
        "pk": 0
      },
      {
        "name": "partner_firma_adi",
        "type": "TEXT",
        "notnull": 1,
        "dflt_value": null,
        "pk": 0
      },
      {
        "name": "partner_siparis_turu",
        "type": "TEXT",
        "notnull": 1,
        "dflt_value": null,
        "pk": 0
      },
      {
        "name": "created_at",
        "type": "DATETIME",
        "notnull": 0,
        "dflt_value": "CURRENT_TIMESTAMP",
        "pk": 0
      },
      {
        "name": "updated_at",
        "type": "DATETIME",
        "notnull": 0,
        "dflt_value": "CURRENT_TIMESTAMP",
        "pk": 0
      }
    ]
  },
  "musteri_raporlari": {
    "columns": [
      {
        "name": "id",
        "type": "INTEGER",
        "notnull": 0,
        "dflt_value": null,
        "pk": 1
      },
      {
        "name": "musteri_id",
        "type": "INTEGER",
        "notnull": 0,
        "dflt_value": null,
        "pk": 0
      },
      {
        "name": "musteri_unvan",
        "type": "TEXT",
        "notnull": 0,
        "dflt_value": null,
        "pk": 0
      },
      {
        "name": "musteri_isim_soyisim",
        "type": "TEXT",
        "notnull": 0,
        "dflt_value": null,
        "pk": 0
      },
      {
        "name": "phone",
        "type": "TEXT",
        "notnull": 0,
        "dflt_value": null,
        "pk": 0
      },
      {
        "name": "siparis_sayisi",
        "type": "INTEGER",
        "notnull": 0,
        "dflt_value": "1",
        "pk": 0
      },
      {
        "name": "toplam_kazanc",
        "type": "DECIMAL(10,2)",
        "notnull": 0,
        "dflt_value": "0",
        "pk": 0
      },
      {
        "name": "ortalama_tutar",
        "type": "DECIMAL(10,2)",
        "notnull": 0,
        "dflt_value": "0",
        "pk": 0
      },
      {
        "name": "son_siparis_tarihi",
        "type": "DATETIME",
        "notnull": 0,
        "dflt_value": null,
        "pk": 0
      },
      {
        "name": "tenant_id",
        "type": "INTEGER",
        "notnull": 0,
        "dflt_value": null,
        "pk": 0
      },
      {
        "name": "created_at",
        "type": "DATETIME",
        "notnull": 0,
        "dflt_value": "CURRENT_TIMESTAMP",
        "pk": 0
      },
      {
        "name": "updated_at",
        "type": "DATETIME",
        "notnull": 0,
        "dflt_value": "CURRENT_TIMESTAMP",
        "pk": 0
      }
    ]
  },
  "organizasyon_kartlar": {
    "columns": [
      {
        "name": "tenant_id",
        "type": "INTEGER",
        "notnull": 0,
        "dflt_value": "1",
        "pk": 0
      },
      {
        "name": "id",
        "type": "INTEGER",
        "notnull": 0,
        "dflt_value": null,
        "pk": 1
      },
      {
        "name": "organizasyon_teslim_tarih",
        "type": "NUM",
        "notnull": 0,
        "dflt_value": null,
        "pk": 0
      },
      {
        "name": "organizasyon_teslim_saat",
        "type": "NUM",
        "notnull": 0,
        "dflt_value": null,
        "pk": 0
      },
      {
        "name": "organizasyon_kart_tur",
        "type": "TEXT",
        "notnull": 0,
        "dflt_value": null,
        "pk": 0
      },
      {
        "name": "organizasyon_alt_tur",
        "type": "TEXT",
        "notnull": 0,
        "dflt_value": null,
        "pk": 0
      },
      {
        "name": "organizasyon_kart_etiket",
        "type": "TEXT",
        "notnull": 0,
        "dflt_value": null,
        "pk": 0
      },
      {
        "name": "organizasyon_il",
        "type": "TEXT",
        "notnull": 0,
        "dflt_value": null,
        "pk": 0
      },
      {
        "name": "organizasyon_ilce",
        "type": "TEXT",
        "notnull": 0,
        "dflt_value": null,
        "pk": 0
      },
      {
        "name": "organizasyon_mahalle",
        "type": "TEXT",
        "notnull": 0,
        "dflt_value": null,
        "pk": 0
      },
      {
        "name": "organizasyon_teslimat_konumu",
        "type": "TEXT",
        "notnull": 0,
        "dflt_value": null,
        "pk": 0
      },
      {
        "name": "organizasyon_acik_adres",
        "type": "TEXT",
        "notnull": 0,
        "dflt_value": null,
        "pk": 0
      },
      {
        "name": "organizasyon_teslim_kisisi",
        "type": "TEXT",
        "notnull": 0,
        "dflt_value": null,
        "pk": 0
      },
      {
        "name": "organizasyon_teslim_kisisi_telefon",
        "type": "TEXT",
        "notnull": 0,
        "dflt_value": null,
        "pk": 0
      },
      {
        "name": "organizasyon_davetiye_gorsel",
        "type": "TEXT",
        "notnull": 0,
        "dflt_value": null,
        "pk": 0
      },
      {
        "name": "organizasyon_teslim_foto_sayisi",
        "type": "INT",
        "notnull": 0,
        "dflt_value": null,
        "pk": 0
      },
      {
        "name": "organizasyon_teslim_fotolar",
        "type": "TEXT",
        "notnull": 0,
        "dflt_value": null,
        "pk": 0
      },
      {
        "name": "organizasyon_toplam_siparis_sayisi",
        "type": "INT",
        "notnull": 0,
        "dflt_value": null,
        "pk": 0
      },
      {
        "name": "organizasyon_status",
        "type": "TEXT",
        "notnull": 0,
        "dflt_value": null,
        "pk": 0
      },
      {
        "name": "arsivli",
        "type": "INTEGER",
        "notnull": 0,
        "dflt_value": "0",
        "pk": 0
      },
      {
        "name": "arsivleme_sebebi",
        "type": "TEXT",
        "notnull": 0,
        "dflt_value": null,
        "pk": 0
      },
      {
        "name": "arsivleme_tarih",
        "type": "DATETIME",
        "notnull": 0,
        "dflt_value": null,
        "pk": 0
      },
      {
        "name": "created_at",
        "type": "DATETIME",
        "notnull": 0,
        "dflt_value": null,
        "pk": 0
      },
      {
        "name": "updated_at",
        "type": "DATETIME",
        "notnull": 0,
        "dflt_value": null,
        "pk": 0
      },
      {
        "name": "created_by",
        "type": "TEXT",
        "notnull": 0,
        "dflt_value": null,
        "pk": 0
      },
      {
        "name": "updated_by",
        "type": "TEXT",
        "notnull": 0,
        "dflt_value": null,
        "pk": 0
      },
      {
        "name": "notes",
        "type": "TEXT",
        "notnull": 0,
        "dflt_value": null,
        "pk": 0
      },
      {
        "name": "is_active",
        "type": "INT",
        "notnull": 0,
        "dflt_value": null,
        "pk": 0
      }
    ]
  },
  "ayarlar_genel_yazdirma_ayarlari": {
    "columns": [
      {
        "name": "tenant_id",
        "type": "INTEGER",
        "notnull": 1,
        "dflt_value": null,
        "pk": 0
      },
      {
        "name": "id",
        "type": "INTEGER",
        "notnull": 0,
        "dflt_value": null,
        "pk": 1
      },
      {
        "name": "logo_png_path",
        "type": "TEXT",
        "notnull": 0,
        "dflt_value": null,
        "pk": 0
      },
      {
        "name": "created_at",
        "type": "DATETIME",
        "notnull": 0,
        "dflt_value": "CURRENT_TIMESTAMP",
        "pk": 0
      },
      {
        "name": "updated_at",
        "type": "DATETIME",
        "notnull": 0,
        "dflt_value": "CURRENT_TIMESTAMP",
        "pk": 0
      },
      {
        "name": "created_by",
        "type": "TEXT",
        "notnull": 0,
        "dflt_value": null,
        "pk": 0
      },
      {
        "name": "updated_by",
        "type": "TEXT",
        "notnull": 0,
        "dflt_value": null,
        "pk": 0
      },
      {
        "name": "is_active",
        "type": "INTEGER",
        "notnull": 0,
        "dflt_value": "1",
        "pk": 0
      }
    ]
  },
  "kampanyalar": {
    "columns": [
      {
        "name": "tenant_id",
        "type": "INTEGER",
        "notnull": 0,
        "dflt_value": "1",
        "pk": 0
      },
      {
        "name": "id",
        "type": "INTEGER",
        "notnull": 0,
        "dflt_value": null,
        "pk": 1
      },
      {
        "name": "ad",
        "type": "TEXT",
        "notnull": 1,
        "dflt_value": null,
        "pk": 0
      },
      {
        "name": "mesaj",
        "type": "TEXT",
        "notnull": 1,
        "dflt_value": null,
        "pk": 0
      },
      {
        "name": "musteri_grubu",
        "type": "TEXT",
        "notnull": 1,
        "dflt_value": null,
        "pk": 0
      },
      {
        "name": "baslangic_tarihi",
        "type": "DATE",
        "notnull": 1,
        "dflt_value": null,
        "pk": 0
      },
      {
        "name": "bitis_tarihi",
        "type": "DATE",
        "notnull": 1,
        "dflt_value": null,
        "pk": 0
      },
      {
        "name": "kupon_kodu",
        "type": "TEXT",
        "notnull": 0,
        "dflt_value": null,
        "pk": 0
      },
      {
        "name": "gorsel_path",
        "type": "TEXT",
        "notnull": 0,
        "dflt_value": null,
        "pk": 0
      },
      {
        "name": "durum",
        "type": "TEXT",
        "notnull": 0,
        "dflt_value": "'taslak'",
        "pk": 0
      },
      {
        "name": "gonderildi",
        "type": "INTEGER",
        "notnull": 0,
        "dflt_value": "0",
        "pk": 0
      },
      {
        "name": "gonderim_tarihi",
        "type": "DATETIME",
        "notnull": 0,
        "dflt_value": null,
        "pk": 0
      },
      {
        "name": "toplam_gonderilen",
        "type": "INTEGER",
        "notnull": 0,
        "dflt_value": "0",
        "pk": 0
      },
      {
        "name": "basarili_gonderilen",
        "type": "INTEGER",
        "notnull": 0,
        "dflt_value": "0",
        "pk": 0
      },
      {
        "name": "basarisiz_gonderilen",
        "type": "INTEGER",
        "notnull": 0,
        "dflt_value": "0",
        "pk": 0
      },
      {
        "name": "created_at",
        "type": "DATETIME",
        "notnull": 0,
        "dflt_value": "CURRENT_TIMESTAMP",
        "pk": 0
      },
      {
        "name": "updated_at",
        "type": "DATETIME",
        "notnull": 0,
        "dflt_value": "CURRENT_TIMESTAMP",
        "pk": 0
      },
      {
        "name": "created_by",
        "type": "TEXT",
        "notnull": 0,
        "dflt_value": null,
        "pk": 0
      },
      {
        "name": "updated_by",
        "type": "TEXT",
        "notnull": 0,
        "dflt_value": null,
        "pk": 0
      },
      {
        "name": "is_active",
        "type": "INTEGER",
        "notnull": 0,
        "dflt_value": "1",
        "pk": 0
      }
    ]
  },
  "musteri_tahsilatlar": {
    "columns": [
      {
        "name": "tenant_id",
        "type": "INTEGER",
        "notnull": 0,
        "dflt_value": "1",
        "pk": 0
      },
      {
        "name": "id",
        "type": "INTEGER",
        "notnull": 0,
        "dflt_value": null,
        "pk": 1
      },
      {
        "name": "musteri_id",
        "type": "INTEGER",
        "notnull": 1,
        "dflt_value": null,
        "pk": 0
      },
      {
        "name": "islem_tarihi_saati",
        "type": "DATETIME",
        "notnull": 1,
        "dflt_value": null,
        "pk": 0
      },
      {
        "name": "odeme_yontemi",
        "type": "VARCHAR(50)",
        "notnull": 1,
        "dflt_value": null,
        "pk": 0
      },
      {
        "name": "tahsil_edilen_tutar",
        "type": "DECIMAL(10,2)",
        "notnull": 1,
        "dflt_value": null,
        "pk": 0
      },
      {
        "name": "odeme_yapan_kisi",
        "type": "VARCHAR(255)",
        "notnull": 0,
        "dflt_value": null,
        "pk": 0
      },
      {
        "name": "tahsilat_yapan_kisi",
        "type": "VARCHAR(255)",
        "notnull": 0,
        "dflt_value": null,
        "pk": 0
      },
      {
        "name": "aciklama",
        "type": "TEXT",
        "notnull": 0,
        "dflt_value": null,
        "pk": 0
      },
      {
        "name": "tahsilat_makbuz_no",
        "type": "VARCHAR(100)",
        "notnull": 0,
        "dflt_value": null,
        "pk": 0
      },
      {
        "name": "durum",
        "type": "VARCHAR(50)",
        "notnull": 0,
        "dflt_value": "'kesildi'",
        "pk": 0
      },
      {
        "name": "created_at",
        "type": "DATETIME",
        "notnull": 0,
        "dflt_value": "CURRENT_TIMESTAMP",
        "pk": 0
      },
      {
        "name": "updated_at",
        "type": "DATETIME",
        "notnull": 0,
        "dflt_value": "CURRENT_TIMESTAMP",
        "pk": 0
      },
      {
        "name": "fatura_id",
        "type": "INTEGER",
        "notnull": 0,
        "dflt_value": null,
        "pk": 0
      },
      {
        "name": "fatura_no",
        "type": "TEXT",
        "notnull": 0,
        "dflt_value": null,
        "pk": 0
      },
      {
        "name": "created_by",
        "type": "TEXT",
        "notnull": 0,
        "dflt_value": null,
        "pk": 0
      },
      {
        "name": "updated_by",
        "type": "TEXT",
        "notnull": 0,
        "dflt_value": null,
        "pk": 0
      },
      {
        "name": "is_active",
        "type": "INTEGER",
        "notnull": 0,
        "dflt_value": "1",
        "pk": 0
      }
    ]
  },
  "organizasyon_gruplari": {
    "columns": [
      {
        "name": "tenant_id",
        "type": "INTEGER",
        "notnull": 0,
        "dflt_value": "1",
        "pk": 0
      },
      {
        "name": "id",
        "type": "INTEGER",
        "notnull": 0,
        "dflt_value": null,
        "pk": 1
      },
      {
        "name": "grup_adi",
        "type": "TEXT",
        "notnull": 1,
        "dflt_value": null,
        "pk": 0
      },
      {
        "name": "renk_kodu",
        "type": "TEXT",
        "notnull": 0,
        "dflt_value": "'#F64798'",
        "pk": 0
      },
      {
        "name": "created_at",
        "type": "DATETIME",
        "notnull": 0,
        "dflt_value": "CURRENT_TIMESTAMP",
        "pk": 0
      },
      {
        "name": "updated_at",
        "type": "DATETIME",
        "notnull": 0,
        "dflt_value": "CURRENT_TIMESTAMP",
        "pk": 0
      },
      {
        "name": "created_by",
        "type": "TEXT",
        "notnull": 0,
        "dflt_value": null,
        "pk": 0
      },
      {
        "name": "updated_by",
        "type": "TEXT",
        "notnull": 0,
        "dflt_value": null,
        "pk": 0
      },
      {
        "name": "is_active",
        "type": "INTEGER",
        "notnull": 0,
        "dflt_value": "1",
        "pk": 0
      }
    ]
  },
  "organizasyon_turleri": {
    "columns": [
      {
        "name": "tenant_id",
        "type": "INTEGER",
        "notnull": 0,
        "dflt_value": "1",
        "pk": 0
      },
      {
        "name": "id",
        "type": "INTEGER",
        "notnull": 0,
        "dflt_value": null,
        "pk": 1
      },
      {
        "name": "grup_id",
        "type": "INTEGER",
        "notnull": 1,
        "dflt_value": null,
        "pk": 0
      },
      {
        "name": "tur_adi",
        "type": "VARCHAR (100)",
        "notnull": 1,
        "dflt_value": null,
        "pk": 0
      },
      {
        "name": "tur_aciklama",
        "type": "TEXT",
        "notnull": 0,
        "dflt_value": null,
        "pk": 0
      },
      {
        "name": "sira_no",
        "type": "INTEGER",
        "notnull": 0,
        "dflt_value": "0",
        "pk": 0
      },
      {
        "name": "created_at",
        "type": "DATETIME",
        "notnull": 0,
        "dflt_value": "CURRENT_TIMESTAMP",
        "pk": 0
      },
      {
        "name": "updated_at",
        "type": "DATETIME",
        "notnull": 0,
        "dflt_value": "CURRENT_TIMESTAMP",
        "pk": 0
      },
      {
        "name": "durum",
        "type": "INTEGER",
        "notnull": 0,
        "dflt_value": "1",
        "pk": 0
      },
      {
        "name": "base_id",
        "type": "INTEGER",
        "notnull": 0,
        "dflt_value": null,
        "pk": 0
      },
      {
        "name": "created_by",
        "type": "TEXT",
        "notnull": 0,
        "dflt_value": null,
        "pk": 0
      },
      {
        "name": "updated_by",
        "type": "TEXT",
        "notnull": 0,
        "dflt_value": null,
        "pk": 0
      },
      {
        "name": "is_active",
        "type": "INTEGER",
        "notnull": 0,
        "dflt_value": "1",
        "pk": 0
      }
    ]
  },
  "partner_firmalar": {
    "columns": [
      {
        "name": "tenant_id",
        "type": "INTEGER",
        "notnull": 0,
        "dflt_value": "1",
        "pk": 0
      },
      {
        "name": "id",
        "type": "INTEGER",
        "notnull": 0,
        "dflt_value": null,
        "pk": 1
      },
      {
        "name": "partner_kodu",
        "type": "TEXT",
        "notnull": 0,
        "dflt_value": null,
        "pk": 0
      },
      {
        "name": "partner_logo",
        "type": "TEXT",
        "notnull": 0,
        "dflt_value": null,
        "pk": 0
      },
      {
        "name": "partner_no",
        "type": "TEXT",
        "notnull": 0,
        "dflt_value": null,
        "pk": 0
      },
      {
        "name": "firma_adi",
        "type": "TEXT",
        "notnull": 1,
        "dflt_value": null,
        "pk": 0
      },
      {
        "name": "partner_yetkili_kisi",
        "type": "TEXT",
        "notnull": 0,
        "dflt_value": null,
        "pk": 0
      },
      {
        "name": "firma_tel",
        "type": "TEXT",
        "notnull": 0,
        "dflt_value": null,
        "pk": 0
      },
      {
        "name": "firma_email",
        "type": "TEXT",
        "notnull": 0,
        "dflt_value": null,
        "pk": 0
      },
      {
        "name": "partner_il",
        "type": "TEXT",
        "notnull": 0,
        "dflt_value": null,
        "pk": 0
      },
      {
        "name": "partner_ilce",
        "type": "TEXT",
        "notnull": 0,
        "dflt_value": null,
        "pk": 0
      },
      {
        "name": "partner_mahalle",
        "type": "TEXT",
        "notnull": 0,
        "dflt_value": null,
        "pk": 0
      },
      {
        "name": "created_at",
        "type": "DATETIME",
        "notnull": 0,
        "dflt_value": "CURRENT_TIMESTAMP",
        "pk": 0
      },
      {
        "name": "updated_at",
        "type": "DATETIME",
        "notnull": 0,
        "dflt_value": "CURRENT_TIMESTAMP",
        "pk": 0
      },
      {
        "name": "firma_logo",
        "type": "TEXT",
        "notnull": 0,
        "dflt_value": null,
        "pk": 0
      },
      {
        "name": "firma_telefon",
        "type": "TEXT",
        "notnull": 0,
        "dflt_value": null,
        "pk": 0
      },
      {
        "name": "firma_adres",
        "type": "TEXT",
        "notnull": 0,
        "dflt_value": null,
        "pk": 0
      },
      {
        "name": "created_by",
        "type": "TEXT",
        "notnull": 0,
        "dflt_value": null,
        "pk": 0
      },
      {
        "name": "updated_by",
        "type": "TEXT",
        "notnull": 0,
        "dflt_value": null,
        "pk": 0
      },
      {
        "name": "is_active",
        "type": "INTEGER",
        "notnull": 0,
        "dflt_value": "1",
        "pk": 0
      }
    ]
  },
  "sicak_satislar": {
    "columns": [
      {
        "name": "tenant_id",
        "type": "INTEGER",
        "notnull": 0,
        "dflt_value": "1",
        "pk": 0
      },
      {
        "name": "id",
        "type": "INTEGER",
        "notnull": 0,
        "dflt_value": null,
        "pk": 1
      },
      {
        "name": "urun_adi",
        "type": "TEXT",
        "notnull": 1,
        "dflt_value": null,
        "pk": 0
      },
      {
        "name": "satis_turu",
        "type": "TEXT",
        "notnull": 1,
        "dflt_value": null,
        "pk": 0
      },
      {
        "name": "tutar",
        "type": "DECIMAL(10,2)",
        "notnull": 1,
        "dflt_value": null,
        "pk": 0
      },
      {
        "name": "miktar",
        "type": "INTEGER",
        "notnull": 0,
        "dflt_value": "1",
        "pk": 0
      },
      {
        "name": "notes",
        "type": "TEXT",
        "notnull": 0,
        "dflt_value": null,
        "pk": 0
      },
      {
        "name": "created_at",
        "type": "DATETIME",
        "notnull": 0,
        "dflt_value": "CURRENT_TIMESTAMP",
        "pk": 0
      },
      {
        "name": "updated_at",
        "type": "DATETIME",
        "notnull": 0,
        "dflt_value": "CURRENT_TIMESTAMP",
        "pk": 0
      },
      {
        "name": "aciklama",
        "type": "TEXT",
        "notnull": 0,
        "dflt_value": null,
        "pk": 0
      },
      {
        "name": "created_by",
        "type": "TEXT",
        "notnull": 0,
        "dflt_value": null,
        "pk": 0
      },
      {
        "name": "updated_by",
        "type": "TEXT",
        "notnull": 0,
        "dflt_value": null,
        "pk": 0
      },
      {
        "name": "is_active",
        "type": "INTEGER",
        "notnull": 0,
        "dflt_value": "1",
        "pk": 0
      }
    ]
  },
  "teknik_destek": {
    "columns": [
      {
        "name": "tenant_id",
        "type": "INTEGER",
        "notnull": 0,
        "dflt_value": "1",
        "pk": 0
      },
      {
        "name": "id",
        "type": "INTEGER",
        "notnull": 0,
        "dflt_value": null,
        "pk": 1
      },
      {
        "name": "konu",
        "type": "TEXT",
        "notnull": 1,
        "dflt_value": null,
        "pk": 0
      },
      {
        "name": "mesaj",
        "type": "TEXT",
        "notnull": 1,
        "dflt_value": null,
        "pk": 0
      },
      {
        "name": "email",
        "type": "TEXT",
        "notnull": 1,
        "dflt_value": null,
        "pk": 0
      },
      {
        "name": "telefon",
        "type": "TEXT",
        "notnull": 0,
        "dflt_value": null,
        "pk": 0
      },
      {
        "name": "oncelik",
        "type": "TEXT",
        "notnull": 0,
        "dflt_value": "'normal'",
        "pk": 0
      },
      {
        "name": "durum",
        "type": "TEXT",
        "notnull": 0,
        "dflt_value": "'beklemede'",
        "pk": 0
      },
      {
        "name": "created_at",
        "type": "DATETIME",
        "notnull": 0,
        "dflt_value": "CURRENT_TIMESTAMP",
        "pk": 0
      },
      {
        "name": "updated_at",
        "type": "DATETIME",
        "notnull": 0,
        "dflt_value": "CURRENT_TIMESTAMP",
        "pk": 0
      },
      {
        "name": "created_by",
        "type": "TEXT",
        "notnull": 0,
        "dflt_value": null,
        "pk": 0
      },
      {
        "name": "updated_by",
        "type": "TEXT",
        "notnull": 0,
        "dflt_value": null,
        "pk": 0
      },
      {
        "name": "is_active",
        "type": "INTEGER",
        "notnull": 0,
        "dflt_value": "1",
        "pk": 0
      }
    ]
  },
  "araclar": {
    "columns": [
      {
        "name": "tenant_id",
        "type": "INTEGER",
        "notnull": 0,
        "dflt_value": "1",
        "pk": 0
      },
      {
        "name": "id",
        "type": "INTEGER",
        "notnull": 0,
        "dflt_value": null,
        "pk": 1
      },
      {
        "name": "plaka",
        "type": "VARCHAR (20)",
        "notnull": 1,
        "dflt_value": null,
        "pk": 0
      },
      {
        "name": "marka",
        "type": "VARCHAR (100)",
        "notnull": 0,
        "dflt_value": null,
        "pk": 0
      },
      {
        "name": "model",
        "type": "VARCHAR (100)",
        "notnull": 0,
        "dflt_value": null,
        "pk": 0
      },
      {
        "name": "renk",
        "type": "VARCHAR (50)",
        "notnull": 0,
        "dflt_value": null,
        "pk": 0
      },
      {
        "name": "yil",
        "type": "INTEGER",
        "notnull": 0,
        "dflt_value": null,
        "pk": 0
      },
      {
        "name": "arac_tipi",
        "type": "VARCHAR (50)",
        "notnull": 0,
        "dflt_value": null,
        "pk": 0
      },
      {
        "name": "created_at",
        "type": "DATETIME",
        "notnull": 0,
        "dflt_value": "CURRENT_TIMESTAMP",
        "pk": 0
      },
      {
        "name": "updated_at",
        "type": "DATETIME",
        "notnull": 0,
        "dflt_value": "CURRENT_TIMESTAMP",
        "pk": 0
      },
      {
        "name": "created_by",
        "type": "TEXT",
        "notnull": 0,
        "dflt_value": null,
        "pk": 0
      },
      {
        "name": "updated_by",
        "type": "TEXT",
        "notnull": 0,
        "dflt_value": null,
        "pk": 0
      },
      {
        "name": "is_active",
        "type": "BOOLEAN",
        "notnull": 0,
        "dflt_value": "\"TRUE\"",
        "pk": 0
      }
    ]
  },
  "ayarlar_genel_teslimat_konumlari": {
    "columns": [
      {
        "name": "tenant_id",
        "type": "INTEGER",
        "notnull": 0,
        "dflt_value": "1",
        "pk": 0
      },
      {
        "name": "id",
        "type": "INTEGER",
        "notnull": 0,
        "dflt_value": null,
        "pk": 1
      },
      {
        "name": "il",
        "type": "TEXT",
        "notnull": 1,
        "dflt_value": null,
        "pk": 0
      },
      {
        "name": "ilce",
        "type": "TEXT",
        "notnull": 1,
        "dflt_value": null,
        "pk": 0
      },
      {
        "name": "konum_adi",
        "type": "TEXT",
        "notnull": 1,
        "dflt_value": null,
        "pk": 0
      },
      {
        "name": "aktif",
        "type": "INTEGER",
        "notnull": 0,
        "dflt_value": "1",
        "pk": 0
      },
      {
        "name": "created_at",
        "type": "DATETIME",
        "notnull": 0,
        "dflt_value": "CURRENT_TIMESTAMP",
        "pk": 0
      },
      {
        "name": "updated_at",
        "type": "DATETIME",
        "notnull": 0,
        "dflt_value": "CURRENT_TIMESTAMP",
        "pk": 0
      },
      {
        "name": "created_by",
        "type": "TEXT",
        "notnull": 0,
        "dflt_value": null,
        "pk": 0
      },
      {
        "name": "updated_by",
        "type": "TEXT",
        "notnull": 0,
        "dflt_value": null,
        "pk": 0
      },
      {
        "name": "is_active",
        "type": "INTEGER",
        "notnull": 0,
        "dflt_value": "1",
        "pk": 0
      }
    ]
  },
  "customers": {
    "columns": [
      {
        "name": "tenant_id",
        "type": "INTEGER",
        "notnull": 0,
        "dflt_value": "1",
        "pk": 0
      },
      {
        "name": "musteri_no",
        "type": "VARCHAR (50)",
        "notnull": 0,
        "dflt_value": null,
        "pk": 0
      },
      {
        "name": "id",
        "type": "INTEGER",
        "notnull": 0,
        "dflt_value": null,
        "pk": 1
      },
      {
        "name": "musteri_unvan",
        "type": "VARCHAR (255)",
        "notnull": 0,
        "dflt_value": null,
        "pk": 0
      },
      {
        "name": "musteri_isim_soyisim",
        "type": "VARCHAR (255)",
        "notnull": 1,
        "dflt_value": null,
        "pk": 0
      },
      {
        "name": "phone",
        "type": "VARCHAR (20)",
        "notnull": 1,
        "dflt_value": null,
        "pk": 0
      },
      {
        "name": "email",
        "type": "VARCHAR (255)",
        "notnull": 0,
        "dflt_value": null,
        "pk": 0
      },
      {
        "name": "address",
        "type": "TEXT",
        "notnull": 0,
        "dflt_value": null,
        "pk": 0
      },
      {
        "name": "neighborhood",
        "type": "VARCHAR (100)",
        "notnull": 0,
        "dflt_value": null,
        "pk": 0
      },
      {
        "name": "district",
        "type": "VARCHAR (100)",
        "notnull": 0,
        "dflt_value": null,
        "pk": 0
      },
      {
        "name": "city",
        "type": "VARCHAR (100)",
        "notnull": 0,
        "dflt_value": null,
        "pk": 0
      },
      {
        "name": "customer_type",
        "type": "VARCHAR (20)",
        "notnull": 0,
        "dflt_value": "'bireysel'",
        "pk": 0
      },
      {
        "name": "musteri_grubu",
        "type": "VARCHAR (100)",
        "notnull": 0,
        "dflt_value": null,
        "pk": 0
      },
      {
        "name": "vergi_kimlik_no",
        "type": "VARCHAR (20)",
        "notnull": 0,
        "dflt_value": null,
        "pk": 0
      },
      {
        "name": "vergi_dairesi",
        "type": "VARCHAR (100)",
        "notnull": 0,
        "dflt_value": null,
        "pk": 0
      },
      {
        "name": "logo_url",
        "type": "VARCHAR (500)",
        "notnull": 0,
        "dflt_value": null,
        "pk": 0
      },
      {
        "name": "musteri_urun_yazisi",
        "type": "TEXT",
        "notnull": 0,
        "dflt_value": null,
        "pk": 0
      },
      {
        "name": "musteri_urun_yazi_dosyalar",
        "type": "TEXT",
        "notnull": 0,
        "dflt_value": null,
        "pk": 0
      },
      {
        "name": "created_at",
        "type": "DATETIME",
        "notnull": 0,
        "dflt_value": "CURRENT_TIMESTAMP",
        "pk": 0
      },
      {
        "name": "updated_at",
        "type": "DATETIME",
        "notnull": 0,
        "dflt_value": "CURRENT_TIMESTAMP",
        "pk": 0
      },
      {
        "name": "created_by",
        "type": "INTEGER",
        "notnull": 0,
        "dflt_value": null,
        "pk": 0
      },
      {
        "name": "updated_by",
        "type": "INTEGER",
        "notnull": 0,
        "dflt_value": null,
        "pk": 0
      },
      {
        "name": "kaydi_duzenleyen",
        "type": "TEXT",
        "notnull": 0,
        "dflt_value": null,
        "pk": 0
      },
      {
        "name": "is_active",
        "type": "INTEGER",
        "notnull": 0,
        "dflt_value": "1",
        "pk": 0
      }
    ]
  },
  "musteri_faturalar": {
    "columns": [
      {
        "name": "tenant_id",
        "type": "INTEGER",
        "notnull": 0,
        "dflt_value": "1",
        "pk": 0
      },
      {
        "name": "id",
        "type": "INTEGER",
        "notnull": 0,
        "dflt_value": null,
        "pk": 1
      },
      {
        "name": "musteri_id",
        "type": "INTEGER",
        "notnull": 1,
        "dflt_value": null,
        "pk": 0
      },
      {
        "name": "fatura_no",
        "type": "VARCHAR(100)",
        "notnull": 1,
        "dflt_value": null,
        "pk": 0
      },
      {
        "name": "fatura_tarihi",
        "type": "DATE",
        "notnull": 1,
        "dflt_value": null,
        "pk": 0
      },
      {
        "name": "siparis_idler",
        "type": "TEXT",
        "notnull": 0,
        "dflt_value": null,
        "pk": 0
      },
      {
        "name": "tutar",
        "type": "DECIMAL(10,2)",
        "notnull": 1,
        "dflt_value": null,
        "pk": 0
      },
      {
        "name": "iskonto_orani",
        "type": "DECIMAL(5,2)",
        "notnull": 0,
        "dflt_value": "0",
        "pk": 0
      },
      {
        "name": "iskonto_tutari",
        "type": "DECIMAL(10,2)",
        "notnull": 0,
        "dflt_value": "0",
        "pk": 0
      },
      {
        "name": "kdv_orani",
        "type": "DECIMAL(5,2)",
        "notnull": 0,
        "dflt_value": "20",
        "pk": 0
      },
      {
        "name": "kdv_tutari",
        "type": "DECIMAL(10,2)",
        "notnull": 0,
        "dflt_value": "0",
        "pk": 0
      },
      {
        "name": "genel_toplam",
        "type": "DECIMAL(10,2)",
        "notnull": 1,
        "dflt_value": null,
        "pk": 0
      },
      {
        "name": "durum",
        "type": "VARCHAR(50)",
        "notnull": 0,
        "dflt_value": "'kesildi'",
        "pk": 0
      },
      {
        "name": "created_at",
        "type": "DATETIME",
        "notnull": 0,
        "dflt_value": "CURRENT_TIMESTAMP",
        "pk": 0
      },
      {
        "name": "updated_at",
        "type": "DATETIME",
        "notnull": 0,
        "dflt_value": "CURRENT_TIMESTAMP",
        "pk": 0
      },
      {
        "name": "created_by",
        "type": "TEXT",
        "notnull": 0,
        "dflt_value": null,
        "pk": 0
      },
      {
        "name": "updated_by",
        "type": "TEXT",
        "notnull": 0,
        "dflt_value": null,
        "pk": 0
      },
      {
        "name": "is_active",
        "type": "INTEGER",
        "notnull": 0,
        "dflt_value": "1",
        "pk": 0
      }
    ]
  },
  "organizasyon_etiketleri": {
    "columns": [
      {
        "name": "tenant_id",
        "type": "INTEGER",
        "notnull": 0,
        "dflt_value": "1",
        "pk": 0
      },
      {
        "name": "id",
        "type": "INTEGER",
        "notnull": 0,
        "dflt_value": null,
        "pk": 1
      },
      {
        "name": "grup_id",
        "type": "INTEGER",
        "notnull": 0,
        "dflt_value": null,
        "pk": 0
      },
      {
        "name": "etiket_adi",
        "type": "VARCHAR (100)",
        "notnull": 1,
        "dflt_value": null,
        "pk": 0
      },
      {
        "name": "sira_no",
        "type": "INTEGER",
        "notnull": 0,
        "dflt_value": "0",
        "pk": 0
      },
      {
        "name": "created_at",
        "type": "DATETIME",
        "notnull": 0,
        "dflt_value": "CURRENT_TIMESTAMP",
        "pk": 0
      },
      {
        "name": "updated_at",
        "type": "DATETIME",
        "notnull": 0,
        "dflt_value": "CURRENT_TIMESTAMP",
        "pk": 0
      },
      {
        "name": "durum",
        "type": "INTEGER",
        "notnull": 0,
        "dflt_value": "1",
        "pk": 0
      },
      {
        "name": "created_by",
        "type": "TEXT",
        "notnull": 0,
        "dflt_value": null,
        "pk": 0
      },
      {
        "name": "updated_by",
        "type": "TEXT",
        "notnull": 0,
        "dflt_value": null,
        "pk": 0
      },
      {
        "name": "is_active",
        "type": "INTEGER",
        "notnull": 0,
        "dflt_value": "1",
        "pk": 0
      }
    ]
  },
  "partner_cari_hareketler": {
    "columns": [
      {
        "name": "tenant_id",
        "type": "INTEGER",
        "notnull": 0,
        "dflt_value": "1",
        "pk": 0
      },
      {
        "name": "id",
        "type": "INTEGER",
        "notnull": 0,
        "dflt_value": null,
        "pk": 1
      },
      {
        "name": "partner_id",
        "type": "INTEGER",
        "notnull": 1,
        "dflt_value": null,
        "pk": 0
      },
      {
        "name": "transaction_type",
        "type": "TEXT",
        "notnull": 1,
        "dflt_value": null,
        "pk": 0
      },
      {
        "name": "payment_method",
        "type": "TEXT",
        "notnull": 0,
        "dflt_value": null,
        "pk": 0
      },
      {
        "name": "amount",
        "type": "REAL",
        "notnull": 1,
        "dflt_value": null,
        "pk": 0
      },
      {
        "name": "responsible_person",
        "type": "TEXT",
        "notnull": 0,
        "dflt_value": null,
        "pk": 0
      },
      {
        "name": "description",
        "type": "TEXT",
        "notnull": 0,
        "dflt_value": null,
        "pk": 0
      },
      {
        "name": "transaction_date",
        "type": "DATETIME",
        "notnull": 1,
        "dflt_value": null,
        "pk": 0
      },
      {
        "name": "created_at",
        "type": "DATETIME",
        "notnull": 0,
        "dflt_value": "CURRENT_TIMESTAMP",
        "pk": 0
      },
      {
        "name": "updated_at",
        "type": "DATETIME",
        "notnull": 0,
        "dflt_value": "CURRENT_TIMESTAMP",
        "pk": 0
      },
      {
        "name": "created_by",
        "type": "TEXT",
        "notnull": 0,
        "dflt_value": null,
        "pk": 0
      },
      {
        "name": "updated_by",
        "type": "TEXT",
        "notnull": 0,
        "dflt_value": null,
        "pk": 0
      },
      {
        "name": "is_active",
        "type": "INTEGER",
        "notnull": 0,
        "dflt_value": "1",
        "pk": 0
      }
    ]
  },
  "product_categories": {
    "columns": [
      {
        "name": "tenant_id",
        "type": "INTEGER",
        "notnull": 0,
        "dflt_value": "1",
        "pk": 0
      },
      {
        "name": "id",
        "type": "INTEGER",
        "notnull": 0,
        "dflt_value": null,
        "pk": 1
      },
      {
        "name": "name",
        "type": "TEXT",
        "notnull": 1,
        "dflt_value": null,
        "pk": 0
      },
      {
        "name": "created_at",
        "type": "DATETIME",
        "notnull": 0,
        "dflt_value": "CURRENT_TIMESTAMP",
        "pk": 0
      },
      {
        "name": "updated_at",
        "type": "DATETIME",
        "notnull": 0,
        "dflt_value": "CURRENT_TIMESTAMP",
        "pk": 0
      },
      {
        "name": "durum",
        "type": "INTEGER",
        "notnull": 0,
        "dflt_value": "1",
        "pk": 0
      },
      {
        "name": "created_by",
        "type": "TEXT",
        "notnull": 0,
        "dflt_value": null,
        "pk": 0
      },
      {
        "name": "updated_by",
        "type": "TEXT",
        "notnull": 0,
        "dflt_value": null,
        "pk": 0
      },
      {
        "name": "is_active",
        "type": "INTEGER",
        "notnull": 0,
        "dflt_value": "1",
        "pk": 0
      }
    ]
  },
  "siparis_kartlar": {
    "columns": [
      {
        "name": "tenant_id",
        "type": "INTEGER",
        "notnull": 0,
        "dflt_value": "1",
        "pk": 0
      },
      {
        "name": "id",
        "type": "INTEGER",
        "notnull": 0,
        "dflt_value": null,
        "pk": 1
      },
      {
        "name": "musteri_id",
        "type": "INTEGER",
        "notnull": 0,
        "dflt_value": null,
        "pk": 0
      },
      {
        "name": "organizasyon_kart_id",
        "type": "INTEGER",
        "notnull": 0,
        "dflt_value": null,
        "pk": 0
      },
      {
        "name": "arsivli",
        "type": "INTEGER",
        "notnull": 0,
        "dflt_value": "0",
        "pk": 0
      },
      {
        "name": "arsivleme_sebebi",
        "type": "TEXT",
        "notnull": 0,
        "dflt_value": null,
        "pk": 0
      },
      {
        "name": "arsivleme_tarih",
        "type": "DATETIME",
        "notnull": 0,
        "dflt_value": null,
        "pk": 0
      },
      {
        "name": "kart_sira",
        "type": "INTEGER",
        "notnull": 0,
        "dflt_value": "0",
        "pk": 0
      },
      {
        "name": "siparis_kodu",
        "type": "TEXT",
        "notnull": 0,
        "dflt_value": null,
        "pk": 0
      },
      {
        "name": "musteri_unvan",
        "type": "TEXT",
        "notnull": 0,
        "dflt_value": null,
        "pk": 0
      },
      {
        "name": "musteri_isim_soyisim",
        "type": "TEXT",
        "notnull": 0,
        "dflt_value": null,
        "pk": 0
      },
      {
        "name": "partner_firma_adi",
        "type": "TEXT",
        "notnull": 0,
        "dflt_value": null,
        "pk": 0
      },
      {
        "name": "partner_siparis_turu",
        "type": "TEXT",
        "notnull": 0,
        "dflt_value": null,
        "pk": 0
      },
      {
        "name": "siparis_veren_telefon",
        "type": "TEXT",
        "notnull": 0,
        "dflt_value": null,
        "pk": 0
      },
      {
        "name": "urun_yazisi",
        "type": "TEXT",
        "notnull": 0,
        "dflt_value": null,
        "pk": 0
      },
      {
        "name": "secilen_urun_yazi_dosyasi",
        "type": "TEXT",
        "notnull": 0,
        "dflt_value": null,
        "pk": 0
      },
      {
        "name": "siparis_urun_id",
        "type": "INTEGER",
        "notnull": 0,
        "dflt_value": null,
        "pk": 0
      },
      {
        "name": "siparis_urun",
        "type": "TEXT",
        "notnull": 0,
        "dflt_value": null,
        "pk": 0
      },
      {
        "name": "siparis_urun_aciklama",
        "type": "TEXT",
        "notnull": 0,
        "dflt_value": null,
        "pk": 0
      },
      {
        "name": "arac_randevu_saat",
        "type": "TEXT",
        "notnull": 0,
        "dflt_value": null,
        "pk": 0
      },
      {
        "name": "arac_markamodel",
        "type": "TEXT",
        "notnull": 0,
        "dflt_value": null,
        "pk": 0
      },
      {
        "name": "arac_renk",
        "type": "TEXT",
        "notnull": 0,
        "dflt_value": null,
        "pk": 0
      },
      {
        "name": "arac_plaka",
        "type": "TEXT",
        "notnull": 0,
        "dflt_value": null,
        "pk": 0
      },
      {
        "name": "siparis_tutari",
        "type": "REAL",
        "notnull": 0,
        "dflt_value": "0",
        "pk": 0
      },
      {
        "name": "odeme_yontemi",
        "type": "TEXT",
        "notnull": 0,
        "dflt_value": "'NAKİT'",
        "pk": 0
      },
      {
        "name": "baglantili_siparisler",
        "type": "TEXT",
        "notnull": 0,
        "dflt_value": null,
        "pk": 0
      },
      {
        "name": "ekstra_ucret_aciklama",
        "type": "TEXT",
        "notnull": 0,
        "dflt_value": null,
        "pk": 0
      },
      {
        "name": "ekstra_ucret_tutari",
        "type": "REAL",
        "notnull": 0,
        "dflt_value": "0",
        "pk": 0
      },
      {
        "name": "toplam_tutar",
        "type": "REAL",
        "notnull": 0,
        "dflt_value": "0",
        "pk": 0
      },
      {
        "name": "teslim_kisisi",
        "type": "TEXT",
        "notnull": 0,
        "dflt_value": null,
        "pk": 0
      },
      {
        "name": "siparis_teslim_kisisi_baskasi",
        "type": "TEXT",
        "notnull": 0,
        "dflt_value": null,
        "pk": 0
      },
      {
        "name": "teslim_kisisi_telefon",
        "type": "TEXT",
        "notnull": 0,
        "dflt_value": null,
        "pk": 0
      },
      {
        "name": "teslim_il",
        "type": "TEXT",
        "notnull": 0,
        "dflt_value": null,
        "pk": 0
      },
      {
        "name": "teslim_ilce",
        "type": "TEXT",
        "notnull": 0,
        "dflt_value": null,
        "pk": 0
      },
      {
        "name": "teslim_mahalle",
        "type": "TEXT",
        "notnull": 0,
        "dflt_value": null,
        "pk": 0
      },
      {
        "name": "teslim_acik_adres",
        "type": "TEXT",
        "notnull": 0,
        "dflt_value": null,
        "pk": 0
      },
      {
        "name": "teslim_saat",
        "type": "TEXT",
        "notnull": 0,
        "dflt_value": null,
        "pk": 0
      },
      {
        "name": "teslim_tarih",
        "type": "TEXT",
        "notnull": 0,
        "dflt_value": null,
        "pk": 0
      },
      {
        "name": "teslim_imza_data",
        "type": "TEXT",
        "notnull": 0,
        "dflt_value": null,
        "pk": 0
      },
      {
        "name": "notes",
        "type": "TEXT",
        "notnull": 0,
        "dflt_value": null,
        "pk": 0
      },
      {
        "name": "status",
        "type": "TEXT",
        "notnull": 0,
        "dflt_value": "'aktif'",
        "pk": 0
      },
      {
        "name": "created_at",
        "type": "DATETIME",
        "notnull": 0,
        "dflt_value": "CURRENT_TIMESTAMP",
        "pk": 0
      },
      {
        "name": "updated_at",
        "type": "DATETIME",
        "notnull": 0,
        "dflt_value": "CURRENT_TIMESTAMP",
        "pk": 0
      },
      {
        "name": "created_by",
        "type": "TEXT",
        "notnull": 0,
        "dflt_value": null,
        "pk": 0
      },
      {
        "name": "updated_by",
        "type": "TEXT",
        "notnull": 0,
        "dflt_value": null,
        "pk": 0
      },
      {
        "name": "is_active",
        "type": "INTEGER",
        "notnull": 0,
        "dflt_value": "1",
        "pk": 0
      }
    ]
  },
  "tenants_abonelik_planlari": {
    "columns": [
      {
        "name": "id",
        "type": "INTEGER",
        "notnull": 0,
        "dflt_value": null,
        "pk": 1
      },
      {
        "name": "plan_adi",
        "type": "TEXT",
        "notnull": 1,
        "dflt_value": null,
        "pk": 0
      },
      {
        "name": "plan_kodu",
        "type": "TEXT",
        "notnull": 1,
        "dflt_value": null,
        "pk": 0
      },
      {
        "name": "aylik_ucret",
        "type": "INTEGER",
        "notnull": 1,
        "dflt_value": null,
        "pk": 0
      },
      {
        "name": "max_kullanici",
        "type": "INTEGER",
        "notnull": 1,
        "dflt_value": "50",
        "pk": 0
      },
      {
        "name": "max_depolama_gb",
        "type": "INTEGER",
        "notnull": 1,
        "dflt_value": "1000",
        "pk": 0
      },
      {
        "name": "ozellikler",
        "type": "TEXT",
        "notnull": 0,
        "dflt_value": null,
        "pk": 0
      },
      {
        "name": "aktif_mi",
        "type": "INTEGER",
        "notnull": 0,
        "dflt_value": "1",
        "pk": 0
      },
      {
        "name": "olusturma_tarihi",
        "type": "DATETIME",
        "notnull": 0,
        "dflt_value": "CURRENT_TIMESTAMP",
        "pk": 0
      },
      {
        "name": "guncelleme_tarihi",
        "type": "DATETIME",
        "notnull": 0,
        "dflt_value": "CURRENT_TIMESTAMP",
        "pk": 0
      }
    ]
  },
  "tenants_kullanimlar": {
    "columns": [
      {
        "name": "id",
        "type": "INTEGER",
        "notnull": 0,
        "dflt_value": null,
        "pk": 1
      },
      {
        "name": "tenant_id",
        "type": "INTEGER",
        "notnull": 1,
        "dflt_value": null,
        "pk": 0
      },
      {
        "name": "kullanici_sayisi",
        "type": "INTEGER",
        "notnull": 0,
        "dflt_value": "0",
        "pk": 0
      },
      {
        "name": "kullanilan_depolama_byte",
        "type": "INTEGER",
        "notnull": 0,
        "dflt_value": "0",
        "pk": 0
      },
      {
        "name": "depolama_limit_byte",
        "type": "INTEGER",
        "notnull": 1,
        "dflt_value": null,
        "pk": 0
      },
      {
        "name": "son_hesaplama_tarihi",
        "type": "DATETIME",
        "notnull": 0,
        "dflt_value": "CURRENT_TIMESTAMP",
        "pk": 0
      },
      {
        "name": "guncelleme_tarihi",
        "type": "DATETIME",
        "notnull": 0,
        "dflt_value": "CURRENT_TIMESTAMP",
        "pk": 0
      }
    ]
  },
  "tenants_fatura_kalemleri": {
    "columns": [
      {
        "name": "id",
        "type": "INTEGER",
        "notnull": 0,
        "dflt_value": null,
        "pk": 1
      },
      {
        "name": "fatura_id",
        "type": "INTEGER",
        "notnull": 1,
        "dflt_value": null,
        "pk": 0
      },
      {
        "name": "kalem_tipi",
        "type": "TEXT",
        "notnull": 1,
        "dflt_value": null,
        "pk": 0
      },
      {
        "name": "aciklama",
        "type": "TEXT",
        "notnull": 1,
        "dflt_value": null,
        "pk": 0
      },
      {
        "name": "miktar",
        "type": "INTEGER",
        "notnull": 0,
        "dflt_value": "1",
        "pk": 0
      },
      {
        "name": "birim_fiyat",
        "type": "INTEGER",
        "notnull": 1,
        "dflt_value": null,
        "pk": 0
      },
      {
        "name": "toplam_fiyat",
        "type": "INTEGER",
        "notnull": 1,
        "dflt_value": null,
        "pk": 0
      },
      {
        "name": "olusturma_tarihi",
        "type": "DATETIME",
        "notnull": 0,
        "dflt_value": "CURRENT_TIMESTAMP",
        "pk": 0
      }
    ]
  },
  "tenants_faturalar": {
    "columns": [
      {
        "name": "id",
        "type": "INTEGER",
        "notnull": 0,
        "dflt_value": null,
        "pk": 1
      },
      {
        "name": "tenant_id",
        "type": "INTEGER",
        "notnull": 1,
        "dflt_value": null,
        "pk": 0
      },
      {
        "name": "fatura_no",
        "type": "TEXT",
        "notnull": 1,
        "dflt_value": null,
        "pk": 0
      },
      {
        "name": "fatura_tarihi",
        "type": "DATE",
        "notnull": 1,
        "dflt_value": null,
        "pk": 0
      },
      {
        "name": "plan_id",
        "type": "INTEGER",
        "notnull": 0,
        "dflt_value": null,
        "pk": 0
      },
      {
        "name": "abonelik_id",
        "type": "INTEGER",
        "notnull": 0,
        "dflt_value": null,
        "pk": 0
      },
      {
        "name": "ara_toplam",
        "type": "INTEGER",
        "notnull": 1,
        "dflt_value": null,
        "pk": 0
      },
      {
        "name": "kdv_tutari",
        "type": "INTEGER",
        "notnull": 0,
        "dflt_value": "0",
        "pk": 0
      },
      {
        "name": "toplam_tutar",
        "type": "INTEGER",
        "notnull": 1,
        "dflt_value": null,
        "pk": 0
      },
      {
        "name": "durum",
        "type": "TEXT",
        "notnull": 1,
        "dflt_value": "'beklemede'",
        "pk": 0
      },
      {
        "name": "odeme_yontemi_id",
        "type": "INTEGER",
        "notnull": 0,
        "dflt_value": null,
        "pk": 0
      },
      {
        "name": "pdf_yolu",
        "type": "TEXT",
        "notnull": 0,
        "dflt_value": null,
        "pk": 0
      },
      {
        "name": "odeme_tarihi",
        "type": "DATETIME",
        "notnull": 0,
        "dflt_value": null,
        "pk": 0
      },
      {
        "name": "vade_tarihi",
        "type": "DATE",
        "notnull": 0,
        "dflt_value": null,
        "pk": 0
      },
      {
        "name": "olusturma_tarihi",
        "type": "DATETIME",
        "notnull": 0,
        "dflt_value": "CURRENT_TIMESTAMP",
        "pk": 0
      },
      {
        "name": "guncelleme_tarihi",
        "type": "DATETIME",
        "notnull": 0,
        "dflt_value": "CURRENT_TIMESTAMP",
        "pk": 0
      }
    ]
  },
  "tenants_logs": {
    "columns": [
      {
        "name": "tenant_id",
        "type": "INTEGER",
        "notnull": 1,
        "dflt_value": null,
        "pk": 0
      },
      {
        "name": "id",
        "type": "INTEGER",
        "notnull": 0,
        "dflt_value": null,
        "pk": 1
      },
      {
        "name": "user",
        "type": "TEXT",
        "notnull": 1,
        "dflt_value": null,
        "pk": 0
      },
      {
        "name": "user_name",
        "type": "TEXT",
        "notnull": 0,
        "dflt_value": null,
        "pk": 0
      },
      {
        "name": "action",
        "type": "TEXT",
        "notnull": 1,
        "dflt_value": null,
        "pk": 0
      },
      {
        "name": "target",
        "type": "TEXT",
        "notnull": 0,
        "dflt_value": null,
        "pk": 0
      },
      {
        "name": "type",
        "type": "TEXT",
        "notnull": 1,
        "dflt_value": null,
        "pk": 0
      },
      {
        "name": "ip_address",
        "type": "TEXT",
        "notnull": 0,
        "dflt_value": null,
        "pk": 0
      },
      {
        "name": "metadata",
        "type": "TEXT",
        "notnull": 0,
        "dflt_value": null,
        "pk": 0
      },
      {
        "name": "created_at",
        "type": "DATETIME",
        "notnull": 0,
        "dflt_value": "CURRENT_TIMESTAMP",
        "pk": 0
      },
      {
        "name": "user_id",
        "type": "INTEGER",
        "notnull": 0,
        "dflt_value": null,
        "pk": 0
      },
      {
        "name": "target_type",
        "type": "TEXT",
        "notnull": 0,
        "dflt_value": null,
        "pk": 0
      },
      {
        "name": "target_id",
        "type": "INTEGER",
        "notnull": 0,
        "dflt_value": null,
        "pk": 0
      },
      {
        "name": "target_name",
        "type": "TEXT",
        "notnull": 0,
        "dflt_value": null,
        "pk": 0
      },
      {
        "name": "details",
        "type": "TEXT",
        "notnull": 0,
        "dflt_value": null,
        "pk": 0
      },
      {
        "name": "user_agent",
        "type": "TEXT",
        "notnull": 0,
        "dflt_value": null,
        "pk": 0
      }
    ]
  },
  "tenants_odeme_yontemleri": {
    "columns": [
      {
        "name": "id",
        "type": "INTEGER",
        "notnull": 0,
        "dflt_value": null,
        "pk": 1
      },
      {
        "name": "tenant_id",
        "type": "INTEGER",
        "notnull": 1,
        "dflt_value": null,
        "pk": 0
      },
      {
        "name": "kart_tipi",
        "type": "TEXT",
        "notnull": 1,
        "dflt_value": null,
        "pk": 0
      },
      {
        "name": "son_dort_rakam",
        "type": "TEXT",
        "notnull": 1,
        "dflt_value": null,
        "pk": 0
      },
      {
        "name": "son_kullanim_ayi",
        "type": "TEXT",
        "notnull": 1,
        "dflt_value": null,
        "pk": 0
      },
      {
        "name": "son_kullanim_yili",
        "type": "INTEGER",
        "notnull": 1,
        "dflt_value": null,
        "pk": 0
      },
      {
        "name": "kart_sahibi_adi",
        "type": "TEXT",
        "notnull": 0,
        "dflt_value": null,
        "pk": 0
      },
      {
        "name": "varsayilan_mi",
        "type": "INTEGER",
        "notnull": 0,
        "dflt_value": "0",
        "pk": 0
      },
      {
        "name": "aktif_mi",
        "type": "INTEGER",
        "notnull": 0,
        "dflt_value": "1",
        "pk": 0
      },
      {
        "name": "olusturma_tarihi",
        "type": "DATETIME",
        "notnull": 0,
        "dflt_value": "CURRENT_TIMESTAMP",
        "pk": 0
      },
      {
        "name": "guncelleme_tarihi",
        "type": "DATETIME",
        "notnull": 0,
        "dflt_value": "CURRENT_TIMESTAMP",
        "pk": 0
      }
    ]
  },
  "tenants": {
    "columns": [
      {
        "name": "id",
        "type": "INTEGER",
        "notnull": 0,
        "dflt_value": null,
        "pk": 1
      },
      {
        "name": "tenants_no",
        "type": "TEXT",
        "notnull": 0,
        "dflt_value": null,
        "pk": 0
      },
      {
        "name": "name",
        "type": "TEXT",
        "notnull": 1,
        "dflt_value": null,
        "pk": 0
      },
      {
        "name": "phone",
        "type": "TEXT",
        "notnull": 0,
        "dflt_value": null,
        "pk": 0
      },
      {
        "name": "email",
        "type": "TEXT",
        "notnull": 0,
        "dflt_value": null,
        "pk": 0
      },
      {
        "name": "city",
        "type": "TEXT",
        "notnull": 0,
        "dflt_value": null,
        "pk": 0
      },
      {
        "name": "state",
        "type": "TEXT",
        "notnull": 0,
        "dflt_value": null,
        "pk": 0
      },
      {
        "name": "settings",
        "type": "TEXT",
        "notnull": 0,
        "dflt_value": null,
        "pk": 0
      },
      {
        "name": "register_date",
        "type": "DATE",
        "notnull": 0,
        "dflt_value": null,
        "pk": 0
      },
      {
        "name": "created_at",
        "type": "DATETIME",
        "notnull": 0,
        "dflt_value": "CURRENT_TIMESTAMP",
        "pk": 0
      },
      {
        "name": "updated_at",
        "type": "DATETIME",
        "notnull": 0,
        "dflt_value": "CURRENT_TIMESTAMP",
        "pk": 0
      },
      {
        "name": "created_by",
        "type": "TEXT",
        "notnull": 0,
        "dflt_value": null,
        "pk": 0
      },
      {
        "name": "updated_by",
        "type": "TEXT",
        "notnull": 0,
        "dflt_value": null,
        "pk": 0
      },
      {
        "name": "status",
        "type": "TEXT",
        "notnull": 0,
        "dflt_value": "aktif",
        "pk": 0
      },
      {
        "name": "is_active",
        "type": "INTEGER",
        "notnull": 0,
        "dflt_value": "1",
        "pk": 0
      }
    ]
  },
  "admin_users": {
    "columns": [
      {
        "name": "id",
        "type": "INTEGER",
        "notnull": 0,
        "dflt_value": null,
        "pk": 1
      },
      {
        "name": "kullaniciadi",
        "type": "TEXT",
        "notnull": 1,
        "dflt_value": null,
        "pk": 0
      },
      {
        "name": "email",
        "type": "TEXT",
        "notnull": 0,
        "dflt_value": null,
        "pk": 0
      },
      {
        "name": "name",
        "type": "TEXT",
        "notnull": 1,
        "dflt_value": null,
        "pk": 0
      },
      {
        "name": "password",
        "type": "TEXT",
        "notnull": 1,
        "dflt_value": null,
        "pk": 0
      },
      {
        "name": "role",
        "type": "TEXT",
        "notnull": 0,
        "dflt_value": "'admin'",
        "pk": 0
      },
      {
        "name": "is_active",
        "type": "INTEGER",
        "notnull": 0,
        "dflt_value": "1",
        "pk": 0
      },
      {
        "name": "profil_resmi",
        "type": "TEXT",
        "notnull": 0,
        "dflt_value": null,
        "pk": 0
      },
      {
        "name": "created_at",
        "type": "DATETIME",
        "notnull": 0,
        "dflt_value": "CURRENT_TIMESTAMP",
        "pk": 0
      },
      {
        "name": "updated_at",
        "type": "DATETIME",
        "notnull": 0,
        "dflt_value": "CURRENT_TIMESTAMP",
        "pk": 0
      },
      {
        "name": "last_login",
        "type": "DATETIME",
        "notnull": 0,
        "dflt_value": null,
        "pk": 0
      }
    ]
  },
  "products": {
    "columns": [
      {
        "name": "tenant_id",
        "type": "INTEGER",
        "notnull": 0,
        "dflt_value": "1",
        "pk": 0
      },
      {
        "name": "id",
        "type": "INTEGER",
        "notnull": 0,
        "dflt_value": null,
        "pk": 1
      },
      {
        "name": "urun_kategori_id",
        "type": "INTEGER",
        "notnull": 0,
        "dflt_value": null,
        "pk": 0
      },
      {
        "name": "urun_adi",
        "type": "TEXT",
        "notnull": 1,
        "dflt_value": null,
        "pk": 0
      },
      {
        "name": "urun_gorseli",
        "type": "TEXT",
        "notnull": 0,
        "dflt_value": null,
        "pk": 0
      },
      {
        "name": "urun_fiyati",
        "type": "DECIMAL (10, 2)",
        "notnull": 0,
        "dflt_value": "0.0",
        "pk": 0
      },
      {
        "name": "created_at",
        "type": "DATETIME",
        "notnull": 0,
        "dflt_value": "CURRENT_TIMESTAMP",
        "pk": 0
      },
      {
        "name": "updated_at",
        "type": "DATETIME",
        "notnull": 0,
        "dflt_value": "CURRENT_TIMESTAMP",
        "pk": 0
      },
      {
        "name": "created_by",
        "type": "TEXT",
        "notnull": 0,
        "dflt_value": "'system'",
        "pk": 0
      },
      {
        "name": "updated_by",
        "type": "TEXT",
        "notnull": 0,
        "dflt_value": "'system'",
        "pk": 0
      },
      {
        "name": "durum",
        "type": "INTEGER",
        "notnull": 0,
        "dflt_value": "'AKTIF'",
        "pk": 0
      },
      {
        "name": "is_active",
        "type": "INTEGER",
        "notnull": 0,
        "dflt_value": "1",
        "pk": 0
      }
    ]
  },
  "arac_takip": {
    "columns": [
      {
        "name": "tenant_id",
        "type": "INTEGER",
        "notnull": 0,
        "dflt_value": "1",
        "pk": 0
      },
      {
        "name": "id",
        "type": "INTEGER",
        "notnull": 0,
        "dflt_value": null,
        "pk": 1
      },
      {
        "name": "arac_id",
        "type": "INTEGER",
        "notnull": 0,
        "dflt_value": null,
        "pk": 0
      },
      {
        "name": "enlem",
        "type": "REAL",
        "notnull": 0,
        "dflt_value": null,
        "pk": 0
      },
      {
        "name": "boylam",
        "type": "REAL",
        "notnull": 0,
        "dflt_value": null,
        "pk": 0
      },
      {
        "name": "hiz",
        "type": "REAL",
        "notnull": 0,
        "dflt_value": null,
        "pk": 0
      },
      {
        "name": "yon",
        "type": "REAL",
        "notnull": 0,
        "dflt_value": null,
        "pk": 0
      },
      {
        "name": "timestamp",
        "type": "DATETIME",
        "notnull": 0,
        "dflt_value": "CURRENT_TIMESTAMP",
        "pk": 0
      },
      {
        "name": "kayit_zamani",
        "type": "DATETIME",
        "notnull": 0,
        "dflt_value": null,
        "pk": 0
      },
      {
        "name": "son_guncelleme",
        "type": "DATETIME",
        "notnull": 0,
        "dflt_value": null,
        "pk": 0
      },
      {
        "name": "guncelleme_zamani",
        "type": "DATETIME",
        "notnull": 0,
        "dflt_value": null,
        "pk": 0
      },
      {
        "name": "konum_adi",
        "type": "TEXT",
        "notnull": 0,
        "dflt_value": null,
        "pk": 0
      }
    ]
  },
  "arac_takip_teslimatlar": {
    "columns": [
      {
        "name": "tenant_id",
        "type": "INTEGER",
        "notnull": 0,
        "dflt_value": "1",
        "pk": 0
      },
      {
        "name": "user_id",
        "type": "INTEGER",
        "notnull": 1,
        "dflt_value": null,
        "pk": 0
      },
      {
        "name": "id",
        "type": "INTEGER",
        "notnull": 0,
        "dflt_value": null,
        "pk": 1
      },
      {
        "name": "arac_id",
        "type": "INTEGER",
        "notnull": 1,
        "dflt_value": null,
        "pk": 0
      },
      {
        "name": "baslangic_konum_lat",
        "type": "REAL",
        "notnull": 0,
        "dflt_value": null,
        "pk": 0
      },
      {
        "name": "baslangic_konum_lng",
        "type": "REAL",
        "notnull": 0,
        "dflt_value": null,
        "pk": 0
      },
      {
        "name": "bitis_konum_lat",
        "type": "REAL",
        "notnull": 0,
        "dflt_value": null,
        "pk": 0
      },
      {
        "name": "bitis_konum_lng",
        "type": "REAL",
        "notnull": 0,
        "dflt_value": null,
        "pk": 0
      },
      {
        "name": "baslangic_zamani",
        "type": "DATETIME",
        "notnull": 0,
        "dflt_value": "CURRENT_TIMESTAMP",
        "pk": 0
      },
      {
        "name": "bitis_zamani",
        "type": "DATETIME",
        "notnull": 0,
        "dflt_value": null,
        "pk": 0
      },
      {
        "name": "durum",
        "type": "TEXT",
        "notnull": 0,
        "dflt_value": "'aktif'",
        "pk": 0
      },
      {
        "name": "updated_at",
        "type": "DATETIME",
        "notnull": 0,
        "dflt_value": "CURRENT_TIMESTAMP",
        "pk": 0
      },
      {
        "name": "kayit_zamani",
        "type": "DATETIME",
        "notnull": 0,
        "dflt_value": null,
        "pk": 0
      },
      {
        "name": "son_guncelleme",
        "type": "DATETIME",
        "notnull": 0,
        "dflt_value": null,
        "pk": 0
      },
      {
        "name": "guncelleme_zamani",
        "type": "DATETIME",
        "notnull": 0,
        "dflt_value": null,
        "pk": 0
      }
    ]
  },
  "users_old_backup": {
    "columns": [
      {
        "name": "tenant_id",
        "type": "INTEGER",
        "notnull": 0,
        "dflt_value": "1",
        "pk": 0
      },
      {
        "name": "id",
        "type": "INTEGER",
        "notnull": 0,
        "dflt_value": null,
        "pk": 1
      },
      {
        "name": "yetki",
        "type": "TEXT",
        "notnull": 0,
        "dflt_value": "'kullanici'",
        "pk": 0
      },
      {
        "name": "role",
        "type": "VARCHAR (20)",
        "notnull": 0,
        "dflt_value": "'user'",
        "pk": 0
      },
      {
        "name": "kullaniciadi",
        "type": "VARCHAR (100)",
        "notnull": 0,
        "dflt_value": null,
        "pk": 0
      },
      {
        "name": "name",
        "type": "VARCHAR (255)",
        "notnull": 1,
        "dflt_value": null,
        "pk": 0
      },
      {
        "name": "surname",
        "type": "TEXT",
        "notnull": 0,
        "dflt_value": null,
        "pk": 0
      },
      {
        "name": "email",
        "type": "VARCHAR (255)",
        "notnull": 1,
        "dflt_value": null,
        "pk": 0
      },
      {
        "name": "telefon",
        "type": "VARCHAR (20)",
        "notnull": 0,
        "dflt_value": null,
        "pk": 0
      },
      {
        "name": "password",
        "type": "VARCHAR (255)",
        "notnull": 1,
        "dflt_value": null,
        "pk": 0
      },
      {
        "name": "profil_resmi",
        "type": "VARCHAR (500)",
        "notnull": 0,
        "dflt_value": null,
        "pk": 0
      },
      {
        "name": "last_login",
        "type": "DATETIME",
        "notnull": 0,
        "dflt_value": null,
        "pk": 0
      },
      {
        "name": "status",
        "type": "TEXT",
        "notnull": 0,
        "dflt_value": "aktif",
        "pk": 0
      },
      {
        "name": "is_active",
        "type": "BOOLEAN",
        "notnull": 0,
        "dflt_value": "\"TRUE\"",
        "pk": 0
      },
      {
        "name": "is_admin",
        "type": "INTEGER",
        "notnull": 0,
        "dflt_value": "0",
        "pk": 0
      },
      {
        "name": "created_at",
        "type": "DATETIME",
        "notnull": 0,
        "dflt_value": "CURRENT_TIMESTAMP",
        "pk": 0
      },
      {
        "name": "updated_at",
        "type": "DATETIME",
        "notnull": 0,
        "dflt_value": "CURRENT_TIMESTAMP",
        "pk": 0
      },
      {
        "name": "created_by",
        "type": "TEXT",
        "notnull": 0,
        "dflt_value": null,
        "pk": 0
      },
      {
        "name": "updated_by",
        "type": "TEXT",
        "notnull": 0,
        "dflt_value": null,
        "pk": 0
      }
    ]
  },
  "users": {
    "columns": [
      {
        "name": "tenant_id",
        "type": "INTEGER",
        "notnull": 0,
        "dflt_value": null,
        "pk": 0
      },
      {
        "name": "id",
        "type": "INTEGER",
        "notnull": 0,
        "dflt_value": null,
        "pk": 1
      },
      {
        "name": "username",
        "type": "TEXT",
        "notnull": 0,
        "dflt_value": null,
        "pk": 0
      },
      {
        "name": "email",
        "type": "TEXT",
        "notnull": 0,
        "dflt_value": null,
        "pk": 0
      },
      {
        "name": "name",
        "type": "TEXT",
        "notnull": 0,
        "dflt_value": null,
        "pk": 0
      },
      {
        "name": "surname",
        "type": "TEXT",
        "notnull": 0,
        "dflt_value": null,
        "pk": 0
      },
      {
        "name": "phone",
        "type": "TEXT",
        "notnull": 0,
        "dflt_value": null,
        "pk": 0
      },
      {
        "name": "role",
        "type": "TEXT",
        "notnull": 0,
        "dflt_value": null,
        "pk": 0
      },
      {
        "name": "password",
        "type": "TEXT",
        "notnull": 0,
        "dflt_value": null,
        "pk": 0
      },
      {
        "name": "profile_image",
        "type": "TEXT",
        "notnull": 0,
        "dflt_value": null,
        "pk": 0
      },
      {
        "name": "status",
        "type": "TEXT",
        "notnull": 0,
        "dflt_value": "'aktif'",
        "pk": 0
      },
      {
        "name": "is_active",
        "type": "INTEGER",
        "notnull": 0,
        "dflt_value": "1",
        "pk": 0
      },
      {
        "name": "is_admin",
        "type": "INTEGER",
        "notnull": 0,
        "dflt_value": "0",
        "pk": 0
      },
      {
        "name": "last_login",
        "type": "DATETIME",
        "notnull": 0,
        "dflt_value": null,
        "pk": 0
      },
      {
        "name": "created_at",
        "type": "DATETIME",
        "notnull": 0,
        "dflt_value": "CURRENT_TIMESTAMP",
        "pk": 0
      },
      {
        "name": "updated_at",
        "type": "DATETIME",
        "notnull": 0,
        "dflt_value": "CURRENT_TIMESTAMP",
        "pk": 0
      }
    ]
  },
  "admin_notifications": {
    "columns": [
      {
        "name": "tenant_id",
        "type": "INTEGER",
        "notnull": 0,
        "dflt_value": null,
        "pk": 0
      },
      {
        "name": "id",
        "type": "INTEGER",
        "notnull": 0,
        "dflt_value": null,
        "pk": 1
      },
      {
        "name": "created_by_user",
        "type": "INTEGER",
        "notnull": 0,
        "dflt_value": null,
        "pk": 0
      },
      {
        "name": "type",
        "type": "TEXT",
        "notnull": 1,
        "dflt_value": "'info'",
        "pk": 0
      },
      {
        "name": "category",
        "type": "TEXT",
        "notnull": 1,
        "dflt_value": "'system'",
        "pk": 0
      },
      {
        "name": "title",
        "type": "TEXT",
        "notnull": 1,
        "dflt_value": null,
        "pk": 0
      },
      {
        "name": "message",
        "type": "TEXT",
        "notnull": 1,
        "dflt_value": null,
        "pk": 0
      },
      {
        "name": "is_read",
        "type": "INTEGER",
        "notnull": 0,
        "dflt_value": "0",
        "pk": 0
      },
      {
        "name": "created_at",
        "type": "DATETIME",
        "notnull": 0,
        "dflt_value": "CURRENT_TIMESTAMP",
        "pk": 0
      },
      {
        "name": "read_at",
        "type": "DATETIME",
        "notnull": 0,
        "dflt_value": null,
        "pk": 0
      }
    ]
  },
  "tenants_abonelikler": {
    "columns": [
      {
        "name": "id",
        "type": "INTEGER",
        "notnull": 0,
        "dflt_value": null,
        "pk": 1
      },
      {
        "name": "tenant_id",
        "type": "INTEGER",
        "notnull": 1,
        "dflt_value": null,
        "pk": 0
      },
      {
        "name": "plan_id",
        "type": "INTEGER",
        "notnull": 1,
        "dflt_value": null,
        "pk": 0
      },
      {
        "name": "durum",
        "type": "TEXT",
        "notnull": 1,
        "dflt_value": "'aktif'",
        "pk": 0
      },
      {
        "name": "aylik_ucret",
        "type": "INTEGER",
        "notnull": 1,
        "dflt_value": null,
        "pk": 0
      },
      {
        "name": "max_kullanici",
        "type": "INTEGER",
        "notnull": 1,
        "dflt_value": null,
        "pk": 0
      },
      {
        "name": "max_depolama_gb",
        "type": "INTEGER",
        "notnull": 1,
        "dflt_value": null,
        "pk": 0
      },
      {
        "name": "mevcut_aylik_toplam",
        "type": "INTEGER",
        "notnull": 0,
        "dflt_value": null,
        "pk": 0
      },
      {
        "name": "indirim_tutari",
        "type": "INTEGER",
        "notnull": 0,
        "dflt_value": "0",
        "pk": 0
      },
      {
        "name": "fatura_dongusu",
        "type": "TEXT",
        "notnull": 0,
        "dflt_value": "'aylik'",
        "pk": 0
      },
      {
        "name": "mevcut_donem_baslangic",
        "type": "DATE",
        "notnull": 0,
        "dflt_value": null,
        "pk": 0
      },
      {
        "name": "mevcut_donem_bitis",
        "type": "DATE",
        "notnull": 0,
        "dflt_value": null,
        "pk": 0
      },
      {
        "name": "sonraki_odeme_tarihi",
        "type": "DATE",
        "notnull": 0,
        "dflt_value": null,
        "pk": 0
      },
      {
        "name": "iptal_tarihi",
        "type": "DATETIME",
        "notnull": 0,
        "dflt_value": null,
        "pk": 0
      },
      {
        "name": "olusturma_tarihi",
        "type": "DATETIME",
        "notnull": 0,
        "dflt_value": "CURRENT_TIMESTAMP",
        "pk": 0
      },
      {
        "name": "guncelleme_tarihi",
        "type": "DATETIME",
        "notnull": 0,
        "dflt_value": "CURRENT_TIMESTAMP",
        "pk": 0
      }
    ]
  },
  "page_permissions": {
    "columns": [
      {
        "name": "id",
        "type": "INTEGER",
        "notnull": 0,
        "dflt_value": null,
        "pk": 1
      },
      {
        "name": "tenant_id",
        "type": "INTEGER",
        "notnull": 1,
        "dflt_value": null,
        "pk": 0
      },
      {
        "name": "role_id",
        "type": "TEXT",
        "notnull": 1,
        "dflt_value": null,
        "pk": 0
      },
      {
        "name": "page_id",
        "type": "TEXT",
        "notnull": 1,
        "dflt_value": null,
        "pk": 0
      },
      {
        "name": "has_access",
        "type": "INTEGER",
        "notnull": 0,
        "dflt_value": "1",
        "pk": 0
      },
      {
        "name": "olusturma_tarihi",
        "type": "DATETIME",
        "notnull": 0,
        "dflt_value": "CURRENT_TIMESTAMP",
        "pk": 0
      },
      {
        "name": "guncelleme_tarihi",
        "type": "DATETIME",
        "notnull": 0,
        "dflt_value": "CURRENT_TIMESTAMP",
        "pk": 0
      }
    ]
  },
  "whatsapp_connections": {
    "columns": [
      {
        "name": "id",
        "type": "INTEGER",
        "notnull": 0,
        "dflt_value": null,
        "pk": 1
      },
      {
        "name": "tenant_id",
        "type": "INTEGER",
        "notnull": 1,
        "dflt_value": null,
        "pk": 0
      },
      {
        "name": "is_connected",
        "type": "INTEGER",
        "notnull": 0,
        "dflt_value": "0",
        "pk": 0
      },
      {
        "name": "phone_number",
        "type": "TEXT",
        "notnull": 0,
        "dflt_value": null,
        "pk": 0
      },
      {
        "name": "user_name",
        "type": "TEXT",
        "notnull": 0,
        "dflt_value": null,
        "pk": 0
      },
      {
        "name": "connected_at",
        "type": "TEXT",
        "notnull": 0,
        "dflt_value": null,
        "pk": 0
      },
      {
        "name": "qr_code",
        "type": "TEXT",
        "notnull": 0,
        "dflt_value": null,
        "pk": 0
      },
      {
        "name": "last_disconnect_reason",
        "type": "TEXT",
        "notnull": 0,
        "dflt_value": null,
        "pk": 0
      },
      {
        "name": "created_at",
        "type": "TEXT",
        "notnull": 0,
        "dflt_value": "CURRENT_TIMESTAMP",
        "pk": 0
      },
      {
        "name": "updated_at",
        "type": "TEXT",
        "notnull": 0,
        "dflt_value": "CURRENT_TIMESTAMP",
        "pk": 0
      }
    ]
  },
  "bildirimler": {
    "columns": [
      {
        "name": "tenant_id",
        "type": "INTEGER",
        "notnull": 0,
        "dflt_value": "1",
        "pk": 0
      },
      {
        "name": "id",
        "type": "INTEGER",
        "notnull": 0,
        "dflt_value": null,
        "pk": 1
      },
      {
        "name": "kullanici_adi",
        "type": "TEXT",
        "notnull": 1,
        "dflt_value": null,
        "pk": 0
      },
      {
        "name": "tip",
        "type": "TEXT",
        "notnull": 1,
        "dflt_value": null,
        "pk": 0
      },
      {
        "name": "baslik",
        "type": "TEXT",
        "notnull": 1,
        "dflt_value": null,
        "pk": 0
      },
      {
        "name": "musteri_adi",
        "type": "TEXT",
        "notnull": 0,
        "dflt_value": null,
        "pk": 0
      },
      {
        "name": "teslim_kisisi",
        "type": "TEXT",
        "notnull": 0,
        "dflt_value": null,
        "pk": 0
      },
      {
        "name": "siparis_teslim_kisisi_baskasi",
        "type": "TEXT",
        "notnull": 0,
        "dflt_value": null,
        "pk": 0
      },
      {
        "name": "siparis_adi",
        "type": "TEXT",
        "notnull": 0,
        "dflt_value": null,
        "pk": 0
      },
      {
        "name": "organizasyon_adi",
        "type": "TEXT",
        "notnull": 0,
        "dflt_value": null,
        "pk": 0
      },
      {
        "name": "siparis_id",
        "type": "INTEGER",
        "notnull": 0,
        "dflt_value": null,
        "pk": 0
      },
      {
        "name": "organizasyon_id",
        "type": "INTEGER",
        "notnull": 0,
        "dflt_value": null,
        "pk": 0
      },
      {
        "name": "musteri_unvani",
        "type": "TEXT",
        "notnull": 0,
        "dflt_value": null,
        "pk": 0
      },
      {
        "name": "organizasyon_alt_tur",
        "type": "TEXT",
        "notnull": 0,
        "dflt_value": null,
        "pk": 0
      },
      {
        "name": "urun_resmi",
        "type": "TEXT",
        "notnull": 0,
        "dflt_value": null,
        "pk": 0
      },
      {
        "name": "is_read",
        "type": "INTEGER",
        "notnull": 0,
        "dflt_value": "0",
        "pk": 0
      },
      {
        "name": "created_at",
        "type": "DATETIME",
        "notnull": 0,
        "dflt_value": "CURRENT_TIMESTAMP",
        "pk": 0
      },
      {
        "name": "arsivleme_sebebi",
        "type": "TEXT",
        "notnull": 0,
        "dflt_value": null,
        "pk": 0
      },
      {
        "name": "mesaj",
        "type": "TEXT",
        "notnull": 0,
        "dflt_value": null,
        "pk": 0
      },
      {
        "name": "link",
        "type": "TEXT",
        "notnull": 0,
        "dflt_value": null,
        "pk": 0
      },
      {
        "name": "created_by",
        "type": "TEXT",
        "notnull": 0,
        "dflt_value": null,
        "pk": 0
      },
      {
        "name": "updated_by",
        "type": "TEXT",
        "notnull": 0,
        "dflt_value": null,
        "pk": 0
      },
      {
        "name": "is_active",
        "type": "INTEGER",
        "notnull": 0,
        "dflt_value": "1",
        "pk": 0
      }
    ]
  },
  "file_uploads": {
    "columns": [
      {
        "name": "tenant_id",
        "type": "INTEGER",
        "notnull": 0,
        "dflt_value": "1",
        "pk": 0
      },
      {
        "name": "id",
        "type": "INTEGER",
        "notnull": 0,
        "dflt_value": null,
        "pk": 1
      },
      {
        "name": "filename",
        "type": "VARCHAR(255)",
        "notnull": 1,
        "dflt_value": null,
        "pk": 0
      },
      {
        "name": "originalname",
        "type": "VARCHAR(255)",
        "notnull": 1,
        "dflt_value": null,
        "pk": 0
      },
      {
        "name": "mimetype",
        "type": "VARCHAR(100)",
        "notnull": 1,
        "dflt_value": null,
        "pk": 0
      },
      {
        "name": "size",
        "type": "INTEGER",
        "notnull": 1,
        "dflt_value": null,
        "pk": 0
      },
      {
        "name": "path",
        "type": "VARCHAR(500)",
        "notnull": 1,
        "dflt_value": null,
        "pk": 0
      },
      {
        "name": "type",
        "type": "VARCHAR(50)",
        "notnull": 0,
        "dflt_value": "'general'",
        "pk": 0
      },
      {
        "name": "entity_id",
        "type": "INTEGER",
        "notnull": 0,
        "dflt_value": null,
        "pk": 0
      },
      {
        "name": "uploaded_by",
        "type": "INTEGER",
        "notnull": 0,
        "dflt_value": null,
        "pk": 0
      },
      {
        "name": "uploaded_at",
        "type": "DATETIME",
        "notnull": 0,
        "dflt_value": "CURRENT_TIMESTAMP",
        "pk": 0
      }
    ]
  },
  "ciceksepeti_orders": {
    "columns": [
      {
        "name": "tenant_id",
        "type": "INTEGER",
        "notnull": 0,
        "dflt_value": "1",
        "pk": 0
      },
      {
        "name": "id",
        "type": "INTEGER",
        "notnull": 0,
        "dflt_value": null,
        "pk": 1
      },
      {
        "name": "siparis_no",
        "type": "TEXT",
        "notnull": 0,
        "dflt_value": null,
        "pk": 0
      },
      {
        "name": "siparis_veren",
        "type": "TEXT",
        "notnull": 0,
        "dflt_value": null,
        "pk": 0
      },
      {
        "name": "siparis_veren_telefon",
        "type": "TEXT",
        "notnull": 0,
        "dflt_value": null,
        "pk": 0
      },
      {
        "name": "teslim_kisi",
        "type": "TEXT",
        "notnull": 0,
        "dflt_value": null,
        "pk": 0
      },
      {
        "name": "teslim_kisi_telefon",
        "type": "TEXT",
        "notnull": 0,
        "dflt_value": null,
        "pk": 0
      },
      {
        "name": "teslim_il",
        "type": "TEXT",
        "notnull": 0,
        "dflt_value": null,
        "pk": 0
      },
      {
        "name": "teslim_ilce",
        "type": "TEXT",
        "notnull": 0,
        "dflt_value": null,
        "pk": 0
      },
      {
        "name": "teslim_mahalle",
        "type": "TEXT",
        "notnull": 0,
        "dflt_value": null,
        "pk": 0
      },
      {
        "name": "teslim_adresi",
        "type": "TEXT",
        "notnull": 0,
        "dflt_value": null,
        "pk": 0
      },
      {
        "name": "urun_adi",
        "type": "TEXT",
        "notnull": 0,
        "dflt_value": null,
        "pk": 0
      },
      {
        "name": "urun_yazisi",
        "type": "TEXT",
        "notnull": 0,
        "dflt_value": null,
        "pk": 0
      },
      {
        "name": "fiyat",
        "type": "DECIMAL (10, 2)",
        "notnull": 0,
        "dflt_value": null,
        "pk": 0
      },
      {
        "name": "teslim_tarihi",
        "type": "DATE",
        "notnull": 0,
        "dflt_value": null,
        "pk": 0
      },
      {
        "name": "teslim_saati",
        "type": "TIME",
        "notnull": 0,
        "dflt_value": null,
        "pk": 0
      },
      {
        "name": "durum",
        "type": "TEXT",
        "notnull": 0,
        "dflt_value": "'beklemede'",
        "pk": 0
      },
      {
        "name": "kaynak",
        "type": "TEXT",
        "notnull": 0,
        "dflt_value": "'Çiçeksepeti'",
        "pk": 0
      },
      {
        "name": "created_at",
        "type": "DATETIME",
        "notnull": 0,
        "dflt_value": "CURRENT_TIMESTAMP",
        "pk": 0
      },
      {
        "name": "updated_at",
        "type": "DATETIME",
        "notnull": 0,
        "dflt_value": "CURRENT_TIMESTAMP",
        "pk": 0
      },
      {
        "name": "created_by",
        "type": "TEXT",
        "notnull": 0,
        "dflt_value": null,
        "pk": 0
      },
      {
        "name": "updated_by",
        "type": "TEXT",
        "notnull": 0,
        "dflt_value": null,
        "pk": 0
      },
      {
        "name": "is_active",
        "type": "INTEGER",
        "notnull": 0,
        "dflt_value": "1",
        "pk": 0
      }
    ]
  }
}